{"id":"58b7cffd-3079-4c7c-a0cd-1c28aaaf278b","name":"白馬カップ","image":"/assets/images/races/016.jpg","startAt":"2024-02-12T02:20:00.000Z","closeAt":"2024-02-12T02:20:00.000Z","entries":[{"id":"0618ec71-74c1-4a3a-8eb1-f51d4389a48c","number":1,"player":{"id":"c611f728-6f12-4535-9979-53897a4670fd","name":"横井容子","shortName":"横井容","image":"/assets/images/players/016.jpg"},"predictionMark":"","first":8,"second":0,"third":0,"others":3,"rockWin":3,"scissorsWin":3,"paperWin":2,"firstRate":72.72727272727273,"thirdRate":72.72727272727273,"comment":"拳を鍛えてきました"},{"id":"6a407152-0698-4eab-be99-00b1e0878648","number":2,"player":{"id":"84648db1-3cfc-4398-9da9-8a607629c1b0","name":"岩谷日向子","shortName":"岩谷日","image":"/assets/images/players/010.jpg"},"predictionMark":"","first":7,"second":5,"third":9,"others":3,"rockWin":7,"scissorsWin":0,"paperWin":0,"firstRate":29.166666666666668,"thirdRate":87.5,"comment":"今日も朝練してきました"},{"id":"e999cb74-1587-4121-bcb3-eb1b0f1494be","number":3,"player":{"id":"41ffbfd8-d0d2-46df-b685-ef64287f5dd3","name":"小村英一","shortName":"小村英","image":"/assets/images/players/008.jpg"},"predictionMark":"","first":9,"second":5,"third":6,"others":3,"rockWin":8,"scissorsWin":0,"paperWin":1,"firstRate":39.130434782608695,"thirdRate":86.95652173913044,"comment":"チョキの力に自信あり"},{"id":"a7fdfb20-5e45-4b3f-a34e-1294f230d0b1","number":4,"player":{"id":"8540b9b4-fd8c-4bc0-8aca-d8f432a26a58","name":"伊藤松夫","shortName":"伊藤松","image":"/assets/images/players/009.jpg"},"predictionMark":"○","first":0,"second":8,"third":3,"others":1,"rockWin":0,"scissorsWin":0,"paperWin":0,"firstRate":0,"thirdRate":91.66666666666666,"comment":"今日も頑張ります"},{"id":"22addd44-e726-4de9-b0f3-d92038504ede","number":5,"player":{"id":"e98eb16a-457d-4792-9a1f-a290965beaf6","name":"中塚雛子","shortName":"中塚雛","image":"/assets/images/players/008.jpg"},"predictionMark":"◎","first":4,"second":0,"third":6,"others":3,"rockWin":4,"scissorsWin":0,"paperWin":0,"firstRate":30.76923076923077,"thirdRate":76.92307692307692,"comment":"自分の癖が見えてきた"},{"id":"16c83cfd-7ccb-4da7-a0d6-e05c265fe396","number":6,"player":{"id":"51255e6c-8cc1-4c86-a7fd-f1fe3971b3a0","name":"大竹愛美","shortName":"大竹愛","image":"/assets/images/players/010.jpg"},"predictionMark":"△","first":4,"second":10,"third":2,"others":6,"rockWin":0,"scissorsWin":3,"paperWin":1,"firstRate":18.181818181818183,"thirdRate":72.72727272727273,"comment":"前回の反省を活かしたい"},{"id":"19250e09-b4a8-42a8-b884-b2dc33113e66","number":7,"player":{"id":"f8b18ce0-dc58-4c92-90a1-ed2767b95fff","name":"内村宏江","shortName":"内村宏","image":"/assets/images/players/011.jpg"},"predictionMark":"","first":9,"second":2,"third":4,"others":8,"rockWin":9,"scissorsWin":0,"paperWin":0,"firstRate":39.130434782608695,"thirdRate":65.21739130434783,"comment":"今日も朝練してきました"},{"id":"f9d58e51-7407-4500-9527-1c639eb57a7e","number":8,"player":{"id":"cd099108-1e10-455c-a2b3-a2172c163e20","name":"仲村泰佑","shortName":"仲村泰","image":"/assets/images/players/001.jpg"},"predictionMark":"","first":5,"second":10,"third":2,"others":1,"rockWin":3,"scissorsWin":2,"paperWin":0,"firstRate":27.77777777777778,"thirdRate":94.44444444444444,"comment":"拳を鍛えてきました"},{"id":"c798609d-3e18-4a7e-a083-e9b38e55b42f","number":9,"player":{"id":"ff557572-18db-4856-acce-31699d1b01ea","name":"緒方優奈","shortName":"緒方優","image":"/assets/images/players/011.jpg"},"predictionMark":"×","first":7,"second":2,"third":10,"others":7,"rockWin":5,"scissorsWin":2,"paperWin":0,"firstRate":26.923076923076923,"thirdRate":73.07692307692308,"comment":"おみくじ大吉でした"}],"trifectaOdds":[{"id":"00219328-1ec0-41f4-b3a8-0176453632d8","type":"trifecta","key":[3,4,7],"odds":81.7},{"id":"0026f5de-835f-4ba0-a5ee-fa314e067b24","type":"trifecta","key":[2,9,8],"odds":210.2},{"id":"02482962-c748-4e61-b07f-12cf3e3d3333","type":"trifecta","key":[5,2,1],"odds":249.8},{"id":"026977d1-0c01-4b64-aad1-80dc2e3899f6","type":"trifecta","key":[4,3,7],"odds":186},{"id":"03c5d78f-1b7a-4645-a8fb-97fdd1c73630","type":"trifecta","key":[3,5,8],"odds":88.6},{"id":"03d15cac-65bb-4ba1-93e0-6bdd882a2873","type":"trifecta","key":[8,7,3],"odds":33.1},{"id":"0432f8e6-3cf6-4bde-b503-b29363ec9bfd","type":"trifecta","key":[9,6,2],"odds":259.9},{"id":"045eb289-b4fb-4ff7-b96f-bff753eecf6e","type":"trifecta","key":[1,3,8],"odds":130.1},{"id":"04907924-336f-4147-8645-9550e4339b41","type":"trifecta","key":[5,8,6],"odds":51.7},{"id":"04910abb-8da9-4d76-9a14-45fce561b0b2","type":"trifecta","key":[9,7,8],"odds":190.6},{"id":"04e8cba2-a114-4f60-8530-a146d4c8b480","type":"trifecta","key":[6,8,1],"odds":143.1},{"id":"05845026-3c6d-4e10-8db3-8117758cd699","type":"trifecta","key":[1,7,3],"odds":296},{"id":"05e3a9d9-c70f-4e57-9b2a-69d3295550da","type":"trifecta","key":[8,6,5],"odds":4.4},{"id":"0611e374-fa22-49e1-a24b-efaede4b5697","type":"trifecta","key":[5,9,2],"odds":89.1},{"id":"06909803-566d-4ff2-abfc-2848ff10089b","type":"trifecta","key":[2,4,3],"odds":162.7},{"id":"0781f169-2b63-48aa-8624-54abaf829d52","type":"trifecta","key":[7,2,1],"odds":101.4},{"id":"0800aadb-be29-4d22-b518-9eb12022031e","type":"trifecta","key":[4,2,5],"odds":261.6},{"id":"08acd201-7b79-4f93-b26b-b9b6c3055e8f","type":"trifecta","key":[7,2,8],"odds":240.7},{"id":"096d383a-f6ac-4b94-8ff8-896d2410cca1","type":"trifecta","key":[9,3,6],"odds":128.6},{"id":"0a6826c5-ca6e-4478-80c9-47bb66ed2a18","type":"trifecta","key":[9,4,8],"odds":159.6},{"id":"0a8c17a8-aa7c-415d-9405-494cabff8467","type":"trifecta","key":[1,9,6],"odds":22.8},{"id":"0ad4aad2-24c6-4216-b4bd-871bc88f5d46","type":"trifecta","key":[7,9,8],"odds":8.5},{"id":"0af63a38-85e2-462f-a30a-9e5c40b283b4","type":"trifecta","key":[3,2,1],"odds":281.5},{"id":"0b211477-2651-44a2-bd34-7b7ac9f5ba76","type":"trifecta","key":[2,1,4],"odds":140.7},{"id":"0b45eb92-438b-4c23-b224-3a32b81a05f3","type":"trifecta","key":[9,5,4],"odds":7.3},{"id":"0c363c1e-a91d-4f69-8ed8-fdc281dd27a9","type":"trifecta","key":[1,2,5],"odds":227.9},{"id":"0d406299-560e-4699-ba7a-f7f85deb4be6","type":"trifecta","key":[1,9,2],"odds":257.4},{"id":"0dac498c-b518-4684-8b73-a03266f438e9","type":"trifecta","key":[8,5,4],"odds":65.1},{"id":"0e029e38-e203-4519-a619-d5f7a696319c","type":"trifecta","key":[1,4,8],"odds":141.2},{"id":"0ee7dd49-1806-4011-8acb-b0feb9534b29","type":"trifecta","key":[8,6,9],"odds":125.8},{"id":"0f837ceb-fb7f-4311-9b84-9d8cf0025cae","type":"trifecta","key":[3,4,5],"odds":151.6},{"id":"0fb7bb92-0d06-4341-a15c-0c34658a404a","type":"trifecta","key":[2,1,7],"odds":192.1},{"id":"10a4ef3b-3eef-48ec-b982-40e7fadfa9af","type":"trifecta","key":[5,9,8],"odds":114.5},{"id":"10f903fa-48a5-49b9-9efc-1b74a0ab9879","type":"trifecta","key":[8,9,4],"odds":74.1},{"id":"11343b04-26c0-41c9-bc0c-5b94d905060d","type":"trifecta","key":[9,8,7],"odds":243.9},{"id":"11c27b75-b5e1-4fa0-953e-cbc7c306ac18","type":"trifecta","key":[9,4,1],"odds":236.2},{"id":"11dd83ca-63be-4040-93bb-7f648a5dbb7b","type":"trifecta","key":[1,5,9],"odds":182.2},{"id":"1279a2cb-7672-418b-9946-88e7c376f6dd","type":"trifecta","key":[3,6,7],"odds":17.4},{"id":"13a7dbe2-c448-4568-9d37-604d64f0e053","type":"trifecta","key":[1,8,4],"odds":199.9},{"id":"13cf1f15-86df-4bef-b289-7ebbdb212974","type":"trifecta","key":[8,9,6],"odds":131},{"id":"13eeb1a4-3140-4623-b074-bc6be2a4eee0","type":"trifecta","key":[9,1,7],"odds":65.7},{"id":"1470dc38-bad2-420c-babf-b12bc42d6b3f","type":"trifecta","key":[2,8,3],"odds":9.5},{"id":"14be451f-175d-4628-bcb4-8022e3a46374","type":"trifecta","key":[7,1,5],"odds":163.4},{"id":"14d17523-8d24-4281-a85f-bdaf32c3202b","type":"trifecta","key":[8,6,2],"odds":175.6},{"id":"150a9849-00c0-49a0-9d21-7df6b4aa4205","type":"trifecta","key":[1,9,5],"odds":117.2},{"id":"15f6a628-8c32-4319-ae3b-3f7337baf841","type":"trifecta","key":[4,5,9],"odds":159.6},{"id":"1701f2f1-70cd-42ff-b921-14a2a5170807","type":"trifecta","key":[6,4,8],"odds":27.6},{"id":"18002053-e41f-463f-89bc-9b0292e3151b","type":"trifecta","key":[7,8,6],"odds":190.6},{"id":"18425a33-84bd-4f5d-ad9b-dc7d78310944","type":"trifecta","key":[5,7,2],"odds":144.7},{"id":"184de4a0-c21b-4b02-a7a9-ea945107704f","type":"trifecta","key":[2,7,5],"odds":141.1},{"id":"18570410-a844-42dd-81e5-bd1c36bf3785","type":"trifecta","key":[5,3,8],"odds":118},{"id":"18dcfefe-0dda-4593-a572-f8d6d5b96c3e","type":"trifecta","key":[3,8,9],"odds":161},{"id":"18faf38b-9190-4d6b-a302-902435b2d03d","type":"trifecta","key":[8,3,2],"odds":37},{"id":"1924c9b4-e96f-4053-b7da-062c1b4b4a8d","type":"trifecta","key":[3,2,7],"odds":4.5},{"id":"19c4db77-cbf1-4fca-9c11-83553628805b","type":"trifecta","key":[3,9,2],"odds":254.8},{"id":"1a9d1d3f-c194-43d0-8b09-ab3218f1772c","type":"trifecta","key":[3,7,4],"odds":292.5},{"id":"1ae9b8db-4eaf-41c6-bbbe-875e0e74ab72","type":"trifecta","key":[5,2,8],"odds":227.9},{"id":"1b212110-8234-455a-9642-73ed374d1493","type":"trifecta","key":[6,5,1],"odds":41.3},{"id":"1b326296-4540-4d25-9ac4-b45f9a15caed","type":"trifecta","key":[7,5,3],"odds":151},{"id":"1b4248db-e59d-47a9-8ae7-b6d006d9ca36","type":"trifecta","key":[1,5,3],"odds":249.2},{"id":"1bf46bdc-432e-4ca1-8b74-835fed78fd14","type":"trifecta","key":[4,5,3],"odds":250.3},{"id":"1c250ff4-efab-4e6b-96c6-8acdd251f9eb","type":"trifecta","key":[2,8,7],"odds":101.1},{"id":"1ca85246-2fdd-4511-9a31-89488ec4e232","type":"trifecta","key":[8,9,1],"odds":78.6},{"id":"1d5af5a9-170c-400f-98b3-8f42dc860dd0","type":"trifecta","key":[7,9,2],"odds":284.2},{"id":"1d841cb4-8e73-4e9a-8c7c-a98b9e03cba1","type":"trifecta","key":[9,5,1],"odds":139.5},{"id":"1dc94959-ce36-4265-8d59-12474a331cd9","type":"trifecta","key":[8,1,6],"odds":47.7},{"id":"1f3ea08a-1b7f-4fb4-a0a3-9d27637126f2","type":"trifecta","key":[7,1,8],"odds":35.7},{"id":"1fb88b31-fde3-4844-9b68-01a91e1b148d","type":"trifecta","key":[5,2,6],"odds":179.9},{"id":"1fd6eef8-691c-47e4-92e6-fe3a8c4ebebb","type":"trifecta","key":[7,4,6],"odds":240},{"id":"1fed0b5b-0145-4386-b5ee-d3955b8f8ff8","type":"trifecta","key":[4,8,1],"odds":257.3},{"id":"203f7ec7-2d45-407f-a965-83a4b63f6f35","type":"trifecta","key":[9,2,1],"odds":278.8},{"id":"205f6745-7207-4b37-9e7e-f969d1f315cb","type":"trifecta","key":[3,1,2],"odds":208.9},{"id":"206d69a8-49ca-4a79-a890-99a0579c9830","type":"trifecta","key":[9,6,7],"odds":179.3},{"id":"20f79ff8-0d6f-4820-96b9-f4ff20abef29","type":"trifecta","key":[2,5,9],"odds":55.8},{"id":"21be68e5-1f80-4706-b960-0c976886935e","type":"trifecta","key":[4,2,9],"odds":241.8},{"id":"22a9f58f-4401-412a-89dd-a8d6279eddab","type":"trifecta","key":[1,6,8],"odds":109.1},{"id":"240edbb1-a7c9-41e7-817e-6ec408dd1606","type":"trifecta","key":[7,5,2],"odds":9.3},{"id":"24389686-f568-4780-961d-0f3493b6ebcd","type":"trifecta","key":[2,9,6],"odds":73.5},{"id":"246d5e48-99a5-4d62-a7ae-83b16f6c1559","type":"trifecta","key":[5,7,4],"odds":101.6},{"id":"2479ee96-951c-4d27-a652-272be495492e","type":"trifecta","key":[4,3,1],"odds":144.8},{"id":"24a3a0fb-f9a4-47dc-ac46-bc16c5d48b4f","type":"trifecta","key":[2,8,1],"odds":209},{"id":"259a0b6e-b1a8-4b8a-b1e5-93e6fb5c854e","type":"trifecta","key":[6,3,4],"odds":88.5},{"id":"25db4471-e930-4da0-9392-4016eb93d47b","type":"trifecta","key":[7,6,2],"odds":59.5},{"id":"264a7ce1-d475-49b5-9d4f-f62c005fc6f2","type":"trifecta","key":[4,3,8],"odds":117.4},{"id":"267777a8-61b5-4f80-b396-42ee2e9d7c1d","type":"trifecta","key":[2,4,1],"odds":236},{"id":"27157781-c4e2-41ce-94f6-ad8ca156ea91","type":"trifecta","key":[4,3,5],"odds":88.3},{"id":"27176bd3-3dad-4457-b7f8-5f274a5f6ac7","type":"trifecta","key":[8,1,3],"odds":144.4},{"id":"285bf226-c148-44f2-9ba8-1e4a57870baf","type":"trifecta","key":[4,8,5],"odds":5.1},{"id":"286f4272-96b7-4848-9574-410b0a255d73","type":"trifecta","key":[4,6,7],"odds":182.4},{"id":"289165e3-bd3c-4ed2-813b-e4cd9486a7c9","type":"trifecta","key":[4,6,3],"odds":105.8},{"id":"28aa2224-ca2d-4573-aa43-0386f575cb5f","type":"trifecta","key":[4,9,7],"odds":146.4},{"id":"290ad286-828f-44cb-b830-25386a13d71e","type":"trifecta","key":[5,8,1],"odds":150},{"id":"292f2bb7-4146-4732-abea-41e151f81d31","type":"trifecta","key":[4,7,1],"odds":164.1},{"id":"294eeca5-17d0-4603-b006-437d7f087cc5","type":"trifecta","key":[8,1,2],"odds":253.4},{"id":"299319d8-0fb0-40e9-8aac-5b744456a3ad","type":"trifecta","key":[1,5,4],"odds":150.1},{"id":"299f7af0-9297-452a-903e-a249046992bf","type":"trifecta","key":[2,1,5],"odds":170.8},{"id":"2a24a7d3-b9ce-4d2a-9d05-e78969d2c217","type":"trifecta","key":[1,3,7],"odds":103.3},{"id":"2a5efd2d-18a5-48be-ab3d-f77c26fccc52","type":"trifecta","key":[2,3,7],"odds":75.6},{"id":"2a74c7c9-fca0-4d30-b7a3-57b09f207491","type":"trifecta","key":[4,6,5],"odds":248.4},{"id":"2ca49783-e235-4409-8e31-f623499031f6","type":"trifecta","key":[1,7,5],"odds":62.4},{"id":"2e05166a-b399-4db8-b7c0-9a4611d2863a","type":"trifecta","key":[9,1,4],"odds":80.3},{"id":"2e746066-6551-4033-9783-05d947a67aa0","type":"trifecta","key":[7,6,5],"odds":219.9},{"id":"31036146-792b-4b63-a167-7be4cbc55c1c","type":"trifecta","key":[6,2,3],"odds":118.4},{"id":"32692725-d548-4c86-a667-4af3a9d63486","type":"trifecta","key":[1,6,4],"odds":13.9},{"id":"32ecfd22-3fc2-4ee1-92c5-2255694b546c","type":"trifecta","key":[7,3,9],"odds":14},{"id":"34033a76-9a82-4eac-ab28-efea98eb0743","type":"trifecta","key":[1,9,7],"odds":141.1},{"id":"34090924-3f43-4805-9b24-df124c269f90","type":"trifecta","key":[5,7,3],"odds":74.7},{"id":"3415be94-a09e-45b8-95c1-8a5ca564fac6","type":"trifecta","key":[7,8,2],"odds":254.3},{"id":"34c70c11-0e3d-49e7-91d2-c83222ce2cf2","type":"trifecta","key":[3,6,2],"odds":266.9},{"id":"351470c2-eea7-4c6f-8c7c-dcb152103327","type":"trifecta","key":[2,5,6],"odds":131.8},{"id":"35b683bf-4f4a-476c-a40d-7f30518140bc","type":"trifecta","key":[9,5,7],"odds":150.9},{"id":"374eac84-3383-4b9d-bd12-fd76984dfb6b","type":"trifecta","key":[9,6,1],"odds":6.3},{"id":"376b22b7-b536-4c7c-b32b-3a7056a05d3b","type":"trifecta","key":[2,3,1],"odds":205.8},{"id":"37d8c060-8681-46f5-9f82-3de310267d23","type":"trifecta","key":[2,3,4],"odds":176.1},{"id":"39c1f9ed-4c2f-4854-a005-3d1118838576","type":"trifecta","key":[9,5,2],"odds":165.7},{"id":"3a8eb2a3-7944-442b-bd40-3fde22e90293","type":"trifecta","key":[8,4,6],"odds":262},{"id":"3b1cb9af-a541-4c27-8263-d950a62a3b71","type":"trifecta","key":[3,9,1],"odds":175.8},{"id":"3b3138a7-c512-40ed-a497-7e2119ad08a7","type":"trifecta","key":[2,9,5],"odds":279.7},{"id":"3b8346c5-e591-4f59-afcb-b76b11da4194","type":"trifecta","key":[7,9,4],"odds":286.9},{"id":"3bce306f-f4d3-42af-892f-dff5d8ae04c8","type":"trifecta","key":[5,2,9],"odds":195.2},{"id":"3c33fff1-3be8-4031-8da8-eb2c1b6e28e1","type":"trifecta","key":[3,8,2],"odds":295.6},{"id":"3c5a520b-5270-42ad-9eff-41dcd4038353","type":"trifecta","key":[1,2,3],"odds":269.5},{"id":"3c6fc477-2822-4bb5-a86d-fa9f964db237","type":"trifecta","key":[5,6,3],"odds":178.3},{"id":"3c873490-cba6-4681-bbf9-f61e70e927f1","type":"trifecta","key":[7,6,8],"odds":243.5},{"id":"3d091e56-7651-40c7-a51b-91e7f0d697be","type":"trifecta","key":[2,9,1],"odds":3.7},{"id":"3d5f696c-7940-4ffa-a56d-837aa032bb0f","type":"trifecta","key":[1,5,6],"odds":77.3},{"id":"3dd35409-1740-4e43-9379-4d1ec88a8560","type":"trifecta","key":[5,7,1],"odds":107.4},{"id":"3e080ff7-fd62-4bff-abe7-e08923ec92e3","type":"trifecta","key":[7,4,2],"odds":88.4},{"id":"3f4b0993-58d0-4973-9f08-13a74c94d13f","type":"trifecta","key":[6,3,7],"odds":171.6},{"id":"3f8a1b70-1907-4e19-89c8-51aeaf2efa36","type":"trifecta","key":[7,8,9],"odds":127.6},{"id":"400082d3-4255-445a-a802-7bb18ddea1f4","type":"trifecta","key":[3,4,2],"odds":90.1},{"id":"40898a16-70c8-423a-a9dc-719dd42ca771","type":"trifecta","key":[4,2,1],"odds":160.2},{"id":"41363670-6c21-4ce4-a0a9-422b82dc0c2a","type":"trifecta","key":[9,7,6],"odds":217.7},{"id":"41aca746-a84d-4bf7-b7fd-9d90d7ef0331","type":"trifecta","key":[1,4,7],"odds":105.6},{"id":"41e43510-63f3-4b13-b7ac-b3e0e543ebdc","type":"trifecta","key":[9,1,3],"odds":104.7},{"id":"427a1e68-7c71-41c6-8e7c-5395769089ce","type":"trifecta","key":[9,1,8],"odds":143.6},{"id":"42d1e243-f37a-4846-bce2-e3c6ab47969d","type":"trifecta","key":[1,9,4],"odds":115.2},{"id":"435cce1e-71b9-4e5f-b864-bc7fb8216376","type":"trifecta","key":[6,2,4],"odds":225.7},{"id":"4418cf92-13df-4ea5-9501-8c37ff0917ed","type":"trifecta","key":[5,4,6],"odds":267.1},{"id":"4484ca82-f864-4c3b-9a1b-41df9f4160aa","type":"trifecta","key":[5,2,3],"odds":113.4},{"id":"45d5d471-f05e-472e-b381-aed6f5de41f5","type":"trifecta","key":[1,2,7],"odds":23.6},{"id":"466a4a01-c7eb-4ec7-a68b-2826daa289d5","type":"trifecta","key":[8,7,9],"odds":66.7},{"id":"46c82daf-0063-4344-8af3-13e48f842716","type":"trifecta","key":[6,9,8],"odds":143.4},{"id":"4714486f-f5c0-4fe7-8dc5-ff6078ca3511","type":"trifecta","key":[3,6,4],"odds":20.8},{"id":"4755737a-d222-49f2-97e0-53830866ab12","type":"trifecta","key":[7,6,3],"odds":177.3},{"id":"48748133-3d45-46c4-9c76-5f2803bffe1c","type":"trifecta","key":[6,3,8],"odds":228.2},{"id":"48d40462-a2b4-4750-9955-11a27e2b8b21","type":"trifecta","key":[6,9,7],"odds":286},{"id":"490de48c-1237-4443-8d79-5b9f8a8b56e2","type":"trifecta","key":[8,5,3],"odds":97.9},{"id":"4980c51c-fe9d-424c-9ae5-3781c91dd542","type":"trifecta","key":[1,9,3],"odds":257.4},{"id":"49cd9337-2ff8-4b1a-b49f-cf9d6f74d0a3","type":"trifecta","key":[6,9,1],"odds":219},{"id":"4c1e32c6-bc28-449c-98c4-d37e8ed69ef0","type":"trifecta","key":[7,5,6],"odds":18.5},{"id":"4c8d9893-e99b-4df6-b969-939babe40c20","type":"trifecta","key":[9,8,3],"odds":158},{"id":"4c949dbf-11dd-47e1-b0b7-711fb8268f7c","type":"trifecta","key":[4,1,3],"odds":240.9},{"id":"506f28a2-33d4-440c-8c9f-ec3c94dba263","type":"trifecta","key":[9,7,5],"odds":54.1},{"id":"507692e9-6dae-4638-aa0d-62d70405bb76","type":"trifecta","key":[9,4,3],"odds":11.1},{"id":"5111dc08-10c2-44eb-b2cc-c1f63b6e574a","type":"trifecta","key":[4,7,2],"odds":36.3},{"id":"52a82630-35ea-442f-a49b-bbdc5faba447","type":"trifecta","key":[2,9,4],"odds":251.6},{"id":"54ac9560-b7c3-47d1-92fd-89e40e0d6eba","type":"trifecta","key":[2,5,4],"odds":6.1},{"id":"55d06c4f-fce2-4a32-a429-6ee9870e0800","type":"trifecta","key":[5,6,9],"odds":285.8},{"id":"568747f0-b00d-41d7-a6da-795c564a52aa","type":"trifecta","key":[8,7,1],"odds":253},{"id":"56c3021a-0a8c-423e-91d9-6764dd304e83","type":"trifecta","key":[2,9,3],"odds":215.3},{"id":"57133ff7-3112-490b-b28e-1dc80f759be0","type":"trifecta","key":[8,4,1],"odds":73.6},{"id":"57727589-f6e5-4bd2-9ffc-49e0e953f3a8","type":"trifecta","key":[9,2,4],"odds":260.1},{"id":"57ba0b98-feab-414a-a4f4-62d85b89c4e6","type":"trifecta","key":[5,6,4],"odds":232},{"id":"58b69aeb-42cf-425d-a8cb-8191310600b4","type":"trifecta","key":[2,8,5],"odds":28.4},{"id":"58baac22-8774-4896-8bb0-5255dc5af84c","type":"trifecta","key":[6,2,1],"odds":144.6},{"id":"58e5abbe-4483-47db-ab20-0b76717055c4","type":"trifecta","key":[7,8,5],"odds":161.3},{"id":"594dd3a7-e3df-4df5-9d9d-8e65a838f9ab","type":"trifecta","key":[4,2,6],"odds":267.8},{"id":"59703686-b495-4e11-a7e2-2a7ae2e19b05","type":"trifecta","key":[9,3,4],"odds":98.9},{"id":"5acee33a-dbb7-45c2-9fc2-ea545bed5c88","type":"trifecta","key":[2,1,6],"odds":211.4},{"id":"5b314071-b963-458c-be29-50bcea4759aa","type":"trifecta","key":[3,2,9],"odds":232.6},{"id":"5b69d838-7184-4ff4-9aa5-897b506a084e","type":"trifecta","key":[8,9,2],"odds":72},{"id":"5b96af5d-1f70-4186-b866-dfd71b79efa9","type":"trifecta","key":[3,2,6],"odds":78.1},{"id":"5c5ebfb1-8c15-4f9b-a189-946a6ffb29e4","type":"trifecta","key":[1,9,8],"odds":186.9},{"id":"5ca0ffa9-aaea-4a8c-ba15-fa00f7df36a4","type":"trifecta","key":[4,8,2],"odds":199.7},{"id":"5ced3f70-c95d-4c53-9ab5-7f1064fd3c95","type":"trifecta","key":[6,2,5],"odds":150.6},{"id":"5d476d38-863c-4b92-bbc4-1aa856dfde35","type":"trifecta","key":[5,8,3],"odds":26.5},{"id":"5d4c3b83-79de-47c6-8969-e170c8f1a630","type":"trifecta","key":[7,2,9],"odds":197.8},{"id":"5fc9c45d-1a6a-4a96-8248-0fd57dd2ef52","type":"trifecta","key":[5,2,4],"odds":128.9},{"id":"60824406-2972-4f28-b3ab-3741c0293a17","type":"trifecta","key":[8,6,1],"odds":125.4},{"id":"608b03bd-423a-4ec4-9ef2-340049a207f2","type":"trifecta","key":[8,2,3],"odds":44.9},{"id":"616778d7-7e83-4eaa-8afe-ae9da977d9db","type":"trifecta","key":[3,1,5],"odds":73.1},{"id":"61b653ae-5ed2-4e07-815b-14783e16c5a9","type":"trifecta","key":[8,5,6],"odds":218.6},{"id":"6221d334-7afa-4d20-a74e-8c1e175d8a54","type":"trifecta","key":[2,4,7],"odds":213.1},{"id":"62dcd28e-8ee1-4468-bd1b-dd3755c93e7f","type":"trifecta","key":[2,8,4],"odds":200.6},{"id":"63156e57-69ab-44c8-ae20-ed4b96421c85","type":"trifecta","key":[9,2,3],"odds":236.2},{"id":"63a0b738-1875-4ae3-86bd-e19299117ce9","type":"trifecta","key":[2,1,8],"odds":18.2},{"id":"64a3a7d3-57d8-4e6f-910a-3bb47e0f143d","type":"trifecta","key":[2,6,5],"odds":260.2},{"id":"64cf00f5-a662-49ea-ae28-31fc62390bb5","type":"trifecta","key":[3,7,6],"odds":45.3},{"id":"64f6e204-4fc6-44f0-bbed-6854db11f193","type":"trifecta","key":[4,5,8],"odds":276.7},{"id":"656c8044-3609-41d6-8987-231117a7ce7b","type":"trifecta","key":[6,1,4],"odds":62.8},{"id":"659dbe9c-f223-4ac3-9b0d-b8e4e28b5d95","type":"trifecta","key":[3,7,2],"odds":281.6},{"id":"65a8a155-2cd2-4ebd-b862-2aa07907d08a","type":"trifecta","key":[5,4,1],"odds":92.2},{"id":"66c30ef0-4044-40cb-b360-1d1f01db7cc7","type":"trifecta","key":[7,1,9],"odds":147.6},{"id":"66d3a92c-0c31-4b52-beb8-b5855f23fb30","type":"trifecta","key":[3,9,4],"odds":251.2},{"id":"66e09cc4-8857-4bb2-9204-d67f937afb36","type":"trifecta","key":[8,1,5],"odds":189.9},{"id":"67045a5f-0026-4e09-94e8-2d142f2792a0","type":"trifecta","key":[5,8,2],"odds":184.1},{"id":"680c74ac-8655-4b5d-9c01-7df6a78dca40","type":"trifecta","key":[4,9,8],"odds":260},{"id":"6818e346-c392-4c27-a0fe-d139e04a110e","type":"trifecta","key":[5,9,6],"odds":182.8},{"id":"68c5ea3b-3362-47c7-808b-0eb28ba4a0d1","type":"trifecta","key":[5,6,1],"odds":203.5},{"id":"694a8ea2-0fc7-4aef-87c7-2cdebbe79b6e","type":"trifecta","key":[7,9,6],"odds":191.3},{"id":"69b4944d-4516-4fc2-a4c6-052e21564bf7","type":"trifecta","key":[1,4,9],"odds":236.4},{"id":"69e9ec45-3e83-4cd1-947e-f25ff35f6991","type":"trifecta","key":[5,9,7],"odds":248.2},{"id":"6a554b81-aabd-4946-962c-8e68592ef43a","type":"trifecta","key":[1,8,5],"odds":258.7},{"id":"6a755949-12fa-4904-ba09-2880cf7d19b2","type":"trifecta","key":[1,8,9],"odds":232.9},{"id":"6b733bfd-9279-4059-a9a9-b814e3933eb1","type":"trifecta","key":[9,2,8],"odds":223.7},{"id":"6ba6e328-3bf4-4f65-b842-a0a3a1574852","type":"trifecta","key":[3,2,4],"odds":261.9},{"id":"6bec8d59-a208-4406-aa8d-2423c5603b30","type":"trifecta","key":[4,6,8],"odds":147},{"id":"6c8c7977-f5f3-4360-8750-4728d2432885","type":"trifecta","key":[5,3,4],"odds":105.9},{"id":"6c9ff373-b164-4143-ab22-a06007faf20d","type":"trifecta","key":[9,6,8],"odds":188.3},{"id":"6cff13d6-3433-49bd-a045-07ac3b92684c","type":"trifecta","key":[2,6,3],"odds":140.8},{"id":"6d161c77-3fea-4733-83b3-fc052ed4e40f","type":"trifecta","key":[7,2,5],"odds":266.9},{"id":"6d9d6254-a84e-4e04-892c-59c6e2b3b2af","type":"trifecta","key":[2,3,9],"odds":154.6},{"id":"6df07a60-c1ff-4a37-b8d7-9a44ff5e00fe","type":"trifecta","key":[7,6,4],"odds":262.9},{"id":"6e06683f-eea1-4b08-b0f5-3afcfe1be7c1","type":"trifecta","key":[9,5,3],"odds":236},{"id":"6f2753ab-bfd3-47e6-8985-89c000dede20","type":"trifecta","key":[5,8,9],"odds":80.5},{"id":"6f2e7c22-2ce2-4a60-bfe8-0c2609c75bea","type":"trifecta","key":[6,8,2],"odds":76},{"id":"6fafae94-9c00-4c68-8b03-da74dabcc15e","type":"trifecta","key":[2,4,6],"odds":243.9},{"id":"709d4f64-1e80-419c-a5be-fa6d7dbdfe7f","type":"trifecta","key":[9,2,7],"odds":285.9},{"id":"7147b243-d20a-43f7-8955-4f567a4f1a4d","type":"trifecta","key":[3,2,8],"odds":290.7},{"id":"71b53c6f-7481-4c99-a44b-5214c375b465","type":"trifecta","key":[5,3,1],"odds":64.8},{"id":"71be957c-702d-4dbc-a178-0082bce92053","type":"trifecta","key":[9,1,6],"odds":249.4},{"id":"7217b418-5be4-440a-9c1e-1621827c2cd0","type":"trifecta","key":[4,1,2],"odds":13.4},{"id":"72725554-8e17-4e5c-8683-8cd74465ecdb","type":"trifecta","key":[3,1,8],"odds":101},{"id":"72e49547-efad-43cc-a9ca-ef51d64cfbfa","type":"trifecta","key":[4,5,2],"odds":19.4},{"id":"73135ddb-364f-445a-a6c3-15c5a9afeca1","type":"trifecta","key":[1,6,5],"odds":267.4},{"id":"74a8d4c4-72b4-45a4-802f-b351065d4db1","type":"trifecta","key":[2,6,9],"odds":106.5},{"id":"74de174c-ee8f-402a-974f-a0505e91ae9a","type":"trifecta","key":[2,6,8],"odds":256.9},{"id":"752dcc7b-0d24-4149-b60d-d8e96bea871a","type":"trifecta","key":[8,4,3],"odds":149.5},{"id":"7530cbec-10c9-4cba-aeb4-edbc365de9df","type":"trifecta","key":[7,1,3],"odds":240.5},{"id":"755b8099-31c6-4c91-87b1-313e9ffe7c3c","type":"trifecta","key":[9,3,1],"odds":138.8},{"id":"75872401-36aa-4365-9b89-7f996f9fe26c","type":"trifecta","key":[5,6,2],"odds":134.7},{"id":"76265b02-bd08-4e03-8dd2-ffbbcae1938d","type":"trifecta","key":[4,1,8],"odds":126.6},{"id":"763cb63a-7b79-45a7-b1c9-d705fb389951","type":"trifecta","key":[6,1,7],"odds":67.2},{"id":"766214dc-9989-43db-ad6a-852ba8725ec8","type":"trifecta","key":[3,8,4],"odds":113.6},{"id":"77991f78-e3e1-42ef-a7d3-128577f2ca34","type":"trifecta","key":[6,7,2],"odds":296.1},{"id":"790c26f9-1deb-48c1-b666-ba6dc49be551","type":"trifecta","key":[7,1,6],"odds":23.8},{"id":"79389cb9-3cea-4a94-aadd-299053f021c0","type":"trifecta","key":[9,5,8],"odds":118.6},{"id":"79c72b84-99e8-4e89-9d93-bf7671b86ecc","type":"trifecta","key":[2,3,8],"odds":97.6},{"id":"79c87d36-1f0f-4937-accb-2df5ae41a535","type":"trifecta","key":[5,9,3],"odds":266.6},{"id":"79fcec43-10b7-452f-bf0a-febf5b33455a","type":"trifecta","key":[5,4,9],"odds":298.5},{"id":"7a4d8307-1899-4762-bcc4-5c0451268f00","type":"trifecta","key":[7,2,3],"odds":154.7},{"id":"7a89bad1-7290-462d-abc8-fc2c425c22cb","type":"trifecta","key":[5,3,7],"odds":16.8},{"id":"7bbae9fb-fa38-48d9-aff4-ffef9af756d8","type":"trifecta","key":[6,3,9],"odds":121.4},{"id":"7c7375c9-3ab3-4c02-b7d8-ff5ef9050245","type":"trifecta","key":[1,3,6],"odds":162.7},{"id":"7ce4c988-f976-4beb-9b88-e902df694c80","type":"trifecta","key":[1,4,6],"odds":69.1},{"id":"7d158b8e-6154-4628-af92-fc8c9234735c","type":"trifecta","key":[6,9,4],"odds":72.9},{"id":"7d340d98-51e9-44ea-b361-8d8cc908dfea","type":"trifecta","key":[7,8,1],"odds":177.9},{"id":"7d3cac4f-98bc-4e8f-9ad5-9a8aebba3c0c","type":"trifecta","key":[2,1,3],"odds":4.6},{"id":"7d923da4-eafa-41f0-bc26-ca9d8b126182","type":"trifecta","key":[7,4,3],"odds":231.5},{"id":"7d967c81-82c1-4cd8-8f6b-1f1a7e66e8d5","type":"trifecta","key":[2,7,3],"odds":251.9},{"id":"7e67a9e9-6a4b-45a3-9a2a-ff957dd4b986","type":"trifecta","key":[2,6,7],"odds":247.7},{"id":"7eccac28-4592-42d4-857e-894d51042c82","type":"trifecta","key":[6,1,3],"odds":207.7},{"id":"7f7f8295-69e1-4919-864c-dee29703bb3a","type":"trifecta","key":[2,4,9],"odds":298.9},{"id":"7fa0e61b-b137-48a0-8695-7c816d9889d3","type":"trifecta","key":[3,5,7],"odds":212.8},{"id":"7fb1d2ed-7319-4bb5-bd12-16c0b3b198a3","type":"trifecta","key":[9,6,4],"odds":96},{"id":"7feea79f-b66e-40bf-b66c-80b82888c914","type":"trifecta","key":[6,7,5],"odds":299.5},{"id":"80ffbbac-ab7a-4ad5-8cc8-4e150b76de08","type":"trifecta","key":[2,8,6],"odds":34.4},{"id":"8131ff44-775c-45c7-8afc-75713b20481d","type":"trifecta","key":[3,7,5],"odds":121.8},{"id":"819c62a5-8804-4f90-b424-cf64fabb832a","type":"trifecta","key":[9,3,8],"odds":94.1},{"id":"81f715e2-94f9-45eb-bc79-c422acf1c5be","type":"trifecta","key":[9,4,6],"odds":204.7},{"id":"8330f8ed-d70c-4f3d-a5c8-562a519737a1","type":"trifecta","key":[6,4,2],"odds":156.7},{"id":"85e8f390-9211-4a42-8969-dab767083ce2","type":"trifecta","key":[6,9,5],"odds":87.5},{"id":"862dd784-8554-4305-807e-204d3f23c632","type":"trifecta","key":[1,7,9],"odds":127.6},{"id":"864ca864-0e3c-411d-b8f3-889c5dc1a871","type":"trifecta","key":[8,5,7],"odds":130.1},{"id":"866557b3-9a4d-4c06-a848-ff507f050f59","type":"trifecta","key":[3,9,8],"odds":167.8},{"id":"87238dee-5b09-4b19-98ca-001f5a326da3","type":"trifecta","key":[6,5,3],"odds":283.2},{"id":"87d3dcbd-2491-45f5-85b1-b3f2560d709a","type":"trifecta","key":[7,8,4],"odds":252.2},{"id":"87fac465-adcb-4386-bd1a-74b65c26cda5","type":"trifecta","key":[7,4,5],"odds":155.1},{"id":"89836bd7-a3f3-4816-893b-424aa681f9a7","type":"trifecta","key":[7,3,5],"odds":57.5},{"id":"89fb3aa1-1d8e-4ee2-952e-cb8f8725fa2e","type":"trifecta","key":[9,8,4],"odds":200.7},{"id":"8a12ae90-4f89-41df-a5c2-45d09bdd4001","type":"trifecta","key":[4,5,7],"odds":271.7},{"id":"8a13edab-edf2-4393-9b2d-4a35b4f6dc34","type":"trifecta","key":[5,7,8],"odds":28.5},{"id":"8a52467e-9565-46cd-868d-f238f47b2225","type":"trifecta","key":[3,5,9],"odds":131.7},{"id":"8aca20da-43be-4c00-9258-2f5bb1b2eb6e","type":"trifecta","key":[5,1,2],"odds":64},{"id":"8b1ce966-0434-4c5c-8b5b-b9ada47b65b3","type":"trifecta","key":[9,8,5],"odds":194.7},{"id":"8c75af53-3660-4601-bde4-f50158d6f443","type":"trifecta","key":[6,9,2],"odds":273},{"id":"8ca10ce6-07f6-467e-bc27-cfda8b687910","type":"trifecta","key":[5,1,3],"odds":293.3},{"id":"8cbc4010-6955-457d-aed6-8df1047ebd9e","type":"trifecta","key":[6,8,4],"odds":75.4},{"id":"8d73de66-84d2-4478-afb8-e807e29d8844","type":"trifecta","key":[5,1,8],"odds":133.3},{"id":"8d980245-3856-4af0-940c-df1197bc8131","type":"trifecta","key":[2,6,1],"odds":67.4},{"id":"8f47ec9d-f705-4726-95c5-eb696888ff1f","type":"trifecta","key":[1,8,7],"odds":122.4},{"id":"8fdc827b-1a56-40b2-92a2-eb02965ec57d","type":"trifecta","key":[5,4,8],"odds":275},{"id":"8ff5334c-d463-40dc-87e8-4a49dc44064b","type":"trifecta","key":[9,8,6],"odds":24.1},{"id":"9025b690-311f-4400-90f2-f4143df6fd72","type":"trifecta","key":[8,3,7],"odds":194.4},{"id":"903eceef-e978-4bac-adcc-ff36fcb80a23","type":"trifecta","key":[5,1,7],"odds":179.4},{"id":"9110f1b9-67ec-450b-9cc3-ed01b1dfc375","type":"trifecta","key":[9,2,5],"odds":47.7},{"id":"9167cc21-462c-4fc9-878a-ec59c37b2a29","type":"trifecta","key":[5,1,4],"odds":137.7},{"id":"91a13316-f640-4b9b-ace3-3e59d6137f32","type":"trifecta","key":[2,7,1],"odds":176.1},{"id":"93ce44a8-e28c-4845-a8f8-644c728625be","type":"trifecta","key":[8,9,5],"odds":105.5},{"id":"947bae54-a82c-4dff-abe1-811941de56c4","type":"trifecta","key":[8,5,1],"odds":171.1},{"id":"9496b8fe-9f70-4295-aa40-432d77b1eae1","type":"trifecta","key":[6,5,7],"odds":26.2},{"id":"949ab0ce-d7ef-4b03-87b8-7aa5595b7d75","type":"trifecta","key":[7,5,8],"odds":61.6},{"id":"94fe6533-3867-40a3-9ebf-0accb94d260f","type":"trifecta","key":[4,7,6],"odds":264.3},{"id":"95a52b38-f459-44f7-98ff-bfbf2ef8facb","type":"trifecta","key":[4,7,8],"odds":287.8},{"id":"968c48cb-0d8b-49ae-afdd-11811d4506a3","type":"trifecta","key":[8,6,4],"odds":195.7},{"id":"96920f50-69dc-4a75-b05b-a7ddcac9a849","type":"trifecta","key":[4,3,6],"odds":200.3},{"id":"9697253a-c82a-42b6-bf09-fc957f0b630c","type":"trifecta","key":[5,8,7],"odds":38.6},{"id":"9713bb79-e600-491d-a95f-0e52a7c202af","type":"trifecta","key":[2,6,4],"odds":90.3},{"id":"9726b9c5-0ccf-41e8-92ba-0da8af4a41b2","type":"trifecta","key":[9,1,2],"odds":287.8},{"id":"98d59fc6-55b0-4347-9115-140a464e4b98","type":"trifecta","key":[3,4,6],"odds":25.9},{"id":"99023f8b-95b4-4ec3-a7ed-db09698b8579","type":"trifecta","key":[9,7,3],"odds":62.6},{"id":"99078c93-891c-4730-a809-34cf7d5aca1e","type":"trifecta","key":[4,8,6],"odds":125.6},{"id":"9991ca7e-8ccd-4942-8f38-bb62bc0e7652","type":"trifecta","key":[6,2,8],"odds":37.5},{"id":"99d2ad71-24d1-4811-b3e5-49ddb2b7326c","type":"trifecta","key":[8,4,2],"odds":283.4},{"id":"9a284793-82b0-4749-b742-f485436bcd11","type":"trifecta","key":[4,6,2],"odds":257.4},{"id":"9ad92565-ce06-4e8e-a5fb-23d0a602bcf7","type":"trifecta","key":[2,4,5],"odds":273.1},{"id":"9b124b68-d7a2-42eb-915e-3cc023f5a25a","type":"trifecta","key":[9,7,4],"odds":112.8},{"id":"9b3ed376-3281-466f-81b1-8269d09a9576","type":"trifecta","key":[9,7,1],"odds":109.9},{"id":"9b4b3f7a-232c-4f6d-a761-9631aea54582","type":"trifecta","key":[3,9,5],"odds":16.6},{"id":"9ba5c8ba-8044-498a-bb53-55b25509b874","type":"trifecta","key":[6,5,8],"odds":254},{"id":"9bdf6a6f-b099-477e-a302-d0b692a54367","type":"trifecta","key":[2,7,8],"odds":279.2},{"id":"9cc8a5ae-8ad5-4cfd-bdb5-9a531e08a47b","type":"trifecta","key":[3,5,4],"odds":56.1},{"id":"9d10df14-6615-4ac9-9390-2190624f76b4","type":"trifecta","key":[8,6,7],"odds":51.1},{"id":"9dd1a481-dc4e-4288-86d4-80d1bc7fd506","type":"trifecta","key":[9,8,1],"odds":296.9},{"id":"9dfa4efb-20e6-46a2-bf6c-f1d24f8bc61b","type":"trifecta","key":[8,2,1],"odds":210.8},{"id":"9e0a629c-4d30-4690-b75a-d046d6aa5181","type":"trifecta","key":[2,3,5],"odds":139},{"id":"9e5ab2d0-c0eb-4c43-9a8a-9d18763de81d","type":"trifecta","key":[3,8,5],"odds":252.4},{"id":"9f102ced-bb29-4455-821b-f4ab11b9b809","type":"trifecta","key":[3,1,6],"odds":203.3},{"id":"a12dc215-53fe-45c0-ab8c-d33fe7d6d287","type":"trifecta","key":[8,2,9],"odds":132.8},{"id":"a15c5efd-7ae1-4e20-8fb5-c56104a51bc2","type":"trifecta","key":[4,2,8],"odds":263.9},{"id":"a1e4b805-a0b2-4b19-8152-23b8af0f24da","type":"trifecta","key":[9,4,5],"odds":151.1},{"id":"a21a0852-b963-4cc0-80e8-ee22e139ec10","type":"trifecta","key":[8,6,3],"odds":173.5},{"id":"a2369c67-b172-4652-aca3-7145a65bdd2b","type":"trifecta","key":[3,6,5],"odds":232.9},{"id":"a27aa012-7702-4e9c-a8f5-404648eea41f","type":"trifecta","key":[3,7,8],"odds":18.6},{"id":"a4c431a3-4d72-459f-a9af-69d2753e5a11","type":"trifecta","key":[8,2,6],"odds":39.6},{"id":"a682d3b6-c377-42cd-ad8a-563a47946305","type":"trifecta","key":[4,9,3],"odds":238.8},{"id":"a827015a-68e1-4c16-8911-da48d6c87acb","type":"trifecta","key":[8,4,7],"odds":247.6},{"id":"a82ada92-1c1c-421e-bdab-f86581fa1332","type":"trifecta","key":[3,6,1],"odds":254.9},{"id":"a840ea13-2b46-4904-9919-68b021a349d5","type":"trifecta","key":[4,7,9],"odds":232.9},{"id":"a90997cd-e85c-44ac-83c4-e48b2906ec05","type":"trifecta","key":[4,9,2],"odds":20.3},{"id":"a91ed2c3-9553-414c-9505-3d630e1a45a0","type":"trifecta","key":[3,1,4],"odds":141.9},{"id":"a9645053-842f-4efe-a900-07979a97fdd5","type":"trifecta","key":[9,1,5],"odds":125.6},{"id":"aa0436ef-78b2-4ea2-9b8a-ee45982024b1","type":"trifecta","key":[5,8,4],"odds":173.6},{"id":"ab17b4ad-e047-4ebe-b246-038087c0c6df","type":"trifecta","key":[1,2,8],"odds":166.9},{"id":"ab972c84-2e65-40e5-b5bd-639a0f77a250","type":"trifecta","key":[2,7,4],"odds":101.1},{"id":"ac632e40-36be-448e-abfe-2420165915d4","type":"trifecta","key":[8,1,7],"odds":7.8},{"id":"ac68120a-586f-48dc-92d9-8f0b6aeca5f6","type":"trifecta","key":[8,7,4],"odds":115.8},{"id":"ac7186b0-af90-4a46-8656-5613432c5476","type":"trifecta","key":[1,8,2],"odds":245.6},{"id":"ad001e20-748a-40d9-8bbe-bfe2cc1564ff","type":"trifecta","key":[9,2,6],"odds":226.2},{"id":"ad6b1949-df8b-4525-8f05-0163e68e9a61","type":"trifecta","key":[5,9,4],"odds":218.3},{"id":"ad967409-722e-49fe-bdb7-ad920155a9b4","type":"trifecta","key":[8,3,6],"odds":258.4},{"id":"add3a8e7-bcc8-488c-828e-b0ffc3e87be0","type":"trifecta","key":[5,3,2],"odds":71.4},{"id":"ae4fbace-018c-4f53-89b1-d795842f571a","type":"trifecta","key":[9,5,6],"odds":241.3},{"id":"ae6fca62-8fd0-4830-a8a8-ae121dc9456e","type":"trifecta","key":[7,2,4],"odds":216.2},{"id":"ae91c2f2-5aaa-437c-a720-e40b02facbf6","type":"trifecta","key":[3,4,1],"odds":25.1},{"id":"af4ce161-7157-4b39-8066-2db6dd332e73","type":"trifecta","key":[1,5,2],"odds":204.2},{"id":"af90d0e1-9af5-470a-87ab-9e1c0b6595a3","type":"trifecta","key":[4,9,1],"odds":245.8},{"id":"afd76ff3-87d7-4cbe-b0ef-73ecdde12dda","type":"trifecta","key":[8,2,4],"odds":22.6},{"id":"afe60fba-5829-4dd2-9078-324f29e13a9a","type":"trifecta","key":[6,3,1],"odds":30.6},{"id":"b06ca0bb-5e6f-41d4-ab84-7ae5571e9cc5","type":"trifecta","key":[6,1,5],"odds":197.1},{"id":"b091c8d4-1494-4406-a6c8-e48af4c95e48","type":"trifecta","key":[5,9,1],"odds":254.6},{"id":"b0f91b4b-fe0c-4c71-b98c-498ad14a9a0e","type":"trifecta","key":[1,5,7],"odds":123.1},{"id":"b21e145e-c7e7-4b4a-9a24-cc0fff4a81ec","type":"trifecta","key":[8,7,5],"odds":273.2},{"id":"b2559f3d-c471-4908-9ff6-c3fe24d442bb","type":"trifecta","key":[6,7,1],"odds":1.8},{"id":"b3a96077-933f-4cef-b66b-aae52c1005ff","type":"trifecta","key":[3,2,5],"odds":134.7},{"id":"b479f24f-7744-4f42-8764-85d1aac4400a","type":"trifecta","key":[6,3,5],"odds":23.3},{"id":"b50e8cdd-4507-4570-9a3d-b9e5caabaf20","type":"trifecta","key":[7,3,6],"odds":23.3},{"id":"b610440f-b047-4809-90d6-ba324f4395bb","type":"trifecta","key":[7,1,4],"odds":299},{"id":"b65db5ba-dd17-41af-afff-ed91cc267df7","type":"trifecta","key":[4,7,3],"odds":298.3},{"id":"b7aae2f8-844a-4de3-a841-acadb46e5acf","type":"trifecta","key":[1,5,8],"odds":8.4},{"id":"b7c3da85-7e35-43b2-b91a-96a3f0a5667b","type":"trifecta","key":[8,1,9],"odds":37.6},{"id":"b84a67a0-28af-42d3-aacc-b325d9ef8ed6","type":"trifecta","key":[8,7,2],"odds":197.3},{"id":"b8bb7d86-baea-43c3-bda9-37d7ccfa6f92","type":"trifecta","key":[4,8,3],"odds":237.9},{"id":"b8f8eebc-db95-4510-b585-6b7ba37f4a18","type":"trifecta","key":[4,3,9],"odds":201},{"id":"b95fc1f1-9f91-448c-8899-ea41f2dc23a4","type":"trifecta","key":[6,4,9],"odds":221.4},{"id":"b9b20dcb-b2c4-4953-a30c-e1db942820c5","type":"trifecta","key":[6,4,3],"odds":172.7},{"id":"ba409880-b94c-4e89-b56c-568cfaef9205","type":"trifecta","key":[2,5,7],"odds":279.7},{"id":"baf91eb7-9222-4f80-9684-d9c527bd518a","type":"trifecta","key":[5,2,7],"odds":67.1},{"id":"bb6833f6-95cd-4fc4-96e2-0309eb1ba5fd","type":"trifecta","key":[6,5,2],"odds":255.3},{"id":"bbfae314-e523-41d8-ace9-17ff329c0911","type":"trifecta","key":[5,4,3],"odds":11.2},{"id":"bc665050-b689-46ce-8be2-8ade7e935cd8","type":"trifecta","key":[8,2,7],"odds":53},{"id":"bcde6671-c890-45d2-9f29-04e922ca4ad6","type":"trifecta","key":[1,8,6],"odds":180.9},{"id":"bd55ce32-a837-46a7-9363-d561013922ad","type":"trifecta","key":[4,8,9],"odds":288.6},{"id":"bd8735b1-08be-4a34-b5c3-1c4f10bd9988","type":"trifecta","key":[7,5,9],"odds":140.5},{"id":"be362cc2-f3a4-49ec-a08a-4c745605dbe8","type":"trifecta","key":[8,5,2],"odds":17.1},{"id":"beecfa34-a73a-482b-8d38-3d4b3dd04b39","type":"trifecta","key":[7,3,4],"odds":192.7},{"id":"bf13e2f7-8f92-466e-bcd5-0dfc5dd25ba0","type":"trifecta","key":[7,3,2],"odds":79.2},{"id":"bf1d0f4a-68ae-4ae2-9d1d-42c22348ceb5","type":"trifecta","key":[1,2,9],"odds":59.6},{"id":"bf1f9ec7-4a9b-4565-8e29-b0c53d5b460a","type":"trifecta","key":[3,6,9],"odds":109.4},{"id":"bf200fd1-5efc-4eb4-9b69-2c0c91e6ee5e","type":"trifecta","key":[8,3,1],"odds":272.7},{"id":"bfa24ec3-8cf8-4b53-ad4d-9524d970919e","type":"trifecta","key":[9,3,2],"odds":178.3},{"id":"bfd0d89b-39dd-4fda-8c6b-9b807d641ca4","type":"trifecta","key":[9,4,2],"odds":213.1},{"id":"c1571e2c-0b8a-4716-8d38-1e5ac8fcfc97","type":"trifecta","key":[7,6,1],"odds":299.1},{"id":"c1f83d21-b25f-4dfd-8bdc-930b7e74e60f","type":"trifecta","key":[3,1,9],"odds":255.5},{"id":"c2413ed1-82aa-4da6-8dd8-a752ecaed9d6","type":"trifecta","key":[3,7,9],"odds":196.6},{"id":"c4183269-3da3-4fbd-be9a-03f1c7008a2c","type":"trifecta","key":[3,8,6],"odds":119.6},{"id":"c4aaf65c-65ae-426b-b1fa-6a61c13a26b7","type":"trifecta","key":[1,8,3],"odds":126.7},{"id":"c59a3611-0024-4067-b599-d953379e96bb","type":"trifecta","key":[6,7,8],"odds":271.8},{"id":"c6b94c68-9374-4cae-a539-45e698d38141","type":"trifecta","key":[6,4,7],"odds":95.8},{"id":"c6ece8aa-62da-422b-93ea-069096ef7c32","type":"trifecta","key":[7,5,1],"odds":255.3},{"id":"c76f3ced-472d-4a87-ad7c-934b7e4e7e7f","type":"trifecta","key":[4,3,2],"odds":40.7},{"id":"c7a2d0fd-0690-47c7-9ef8-d1cba7e5fc1a","type":"trifecta","key":[4,7,5],"odds":148},{"id":"c83fd695-5470-4085-8a8c-a32748796f29","type":"trifecta","key":[9,3,7],"odds":68.7},{"id":"c84c86d6-f4cd-4967-b641-98ae501bcae4","type":"trifecta","key":[1,6,7],"odds":181.9},{"id":"ca2f0b70-423d-40bd-a44e-7034a57e44a9","type":"trifecta","key":[9,7,2],"odds":53.2},{"id":"caa10bd2-a354-4253-9cb9-c7da18cdd05b","type":"trifecta","key":[3,8,1],"odds":265.2},{"id":"caf3a5c3-deff-4c7c-a974-11d5e8fe6334","type":"trifecta","key":[6,8,5],"odds":206.5},{"id":"cb650b9d-5b29-491c-8f1d-e2011a636af7","type":"trifecta","key":[6,2,7],"odds":74.2},{"id":"cc97eca1-2a3e-4af7-ac4a-cd8a3acb44cf","type":"trifecta","key":[5,1,9],"odds":31.9},{"id":"cc9ebad5-c748-4101-97be-44c8c06ff37e","type":"trifecta","key":[4,9,5],"odds":279.2},{"id":"cd5928f5-576f-49c6-a8f7-4073c31863a5","type":"trifecta","key":[6,9,3],"odds":11.6},{"id":"cf15561b-13c6-4398-ac0a-d4e8862ca096","type":"trifecta","key":[6,8,9],"odds":87},{"id":"cf585762-f30b-4c5b-ac53-831963231a1e","type":"trifecta","key":[1,7,2],"odds":274.8},{"id":"cfd762a6-ab31-442c-b53e-d7b497e17078","type":"trifecta","key":[5,3,6],"odds":187.1},{"id":"d04b30d7-9df8-46df-a9cf-846f8f879a33","type":"trifecta","key":[6,4,1],"odds":251.3},{"id":"d1977357-4f92-41e2-8230-de5e57d89320","type":"trifecta","key":[2,7,9],"odds":272.4},{"id":"d1978dba-c1c7-4c58-bdc8-d235432852c4","type":"trifecta","key":[8,7,6],"odds":53.4},{"id":"d1c9cbbb-7cae-4d8f-83b6-531a4bbb7b81","type":"trifecta","key":[2,8,9],"odds":176.6},{"id":"d20b618c-6173-4fb3-a51a-c916c509e70f","type":"trifecta","key":[1,3,4],"odds":119.2},{"id":"d4158d8e-4a7a-410a-b3b3-6c0e506f5f4e","type":"trifecta","key":[7,4,1],"odds":70.9},{"id":"d44a2644-c6a1-4b69-9cc7-ff349b33d89e","type":"trifecta","key":[8,9,7],"odds":27.4},{"id":"d44e3553-0536-4789-bb15-70b47345766c","type":"trifecta","key":[5,6,7],"odds":191.4},{"id":"d532365f-bb33-4ebe-ba8c-c2215bf00f34","type":"trifecta","key":[6,7,3],"odds":293.6},{"id":"d554fb3e-de1f-493f-97dc-41a578ab7c7a","type":"trifecta","key":[7,1,2],"odds":212.8},{"id":"d5f140b5-1cd6-49f1-916d-9e9af44ed6f8","type":"trifecta","key":[4,1,9],"odds":21},{"id":"d653aff9-a27c-4432-a580-5644ae92851e","type":"trifecta","key":[2,1,9],"odds":152.2},{"id":"d72d2193-d255-478d-8373-9544ebb10bf8","type":"trifecta","key":[8,2,5],"odds":7.5},{"id":"d73b148a-133b-426f-93fa-7b371913ec5c","type":"trifecta","key":[3,7,1],"odds":109},{"id":"d74b3c4f-5ab2-4358-8c96-32f31bb45f95","type":"trifecta","key":[2,3,6],"odds":48.2},{"id":"d7a42e93-5f41-496a-996d-0183dab735af","type":"trifecta","key":[6,5,9],"odds":230.4},{"id":"d82e2d70-f858-4744-b3ca-9379134db2fc","type":"trifecta","key":[7,4,8],"odds":157.2},{"id":"d84ed6d9-35e2-4c40-8a24-790f983b3ad7","type":"trifecta","key":[3,5,1],"odds":78.5},{"id":"d869ffad-6c05-4e1d-a64f-3536c157e114","type":"trifecta","key":[8,4,9],"odds":191},{"id":"d8e90505-e5f1-4ad8-add5-0c5b873ff5c0","type":"trifecta","key":[6,3,2],"odds":42.2},{"id":"d9310263-1e09-4be9-90f1-ad8db10ed7ce","type":"trifecta","key":[7,8,3],"odds":24.8},{"id":"d9f6a7f0-c726-4d0b-816c-fd001feede21","type":"trifecta","key":[6,7,4],"odds":295.2},{"id":"da13e7da-19c3-42c8-a4eb-12c2879bdb2b","type":"trifecta","key":[5,1,6],"odds":272.3},{"id":"da2467e5-3600-4c6c-8167-0b2e683c5b87","type":"trifecta","key":[3,5,2],"odds":160.8},{"id":"db4911d4-aa83-4515-a665-bb14b55223d4","type":"trifecta","key":[6,4,5],"odds":232.8},{"id":"db7ca63b-ed97-422d-b190-0e2207664cef","type":"trifecta","key":[5,3,9],"odds":262.5},{"id":"dcba4671-6152-4b0d-9cb6-0bb5cdafda8b","type":"trifecta","key":[7,3,1],"odds":264.8},{"id":"dcbd835d-4615-4b9b-9470-a5ef1eabf448","type":"trifecta","key":[4,2,3],"odds":176.9},{"id":"dcc942ce-0f7a-4434-bcd5-f99235e1d765","type":"trifecta","key":[6,1,2],"odds":251.6},{"id":"dd7be92b-d16f-4dd0-9156-3086fe675603","type":"trifecta","key":[6,5,4],"odds":212.8},{"id":"decd2b4c-fe8a-4c11-92d4-01c04fed4fd8","type":"trifecta","key":[4,8,7],"odds":192.1},{"id":"df044c46-9822-44d7-b0eb-641a974cc277","type":"trifecta","key":[1,6,3],"odds":37.4},{"id":"df75050d-09bf-4928-b4a2-d388312a796e","type":"trifecta","key":[1,4,3],"odds":122.3},{"id":"dfa1875b-5472-487d-b4a7-7f320d46905d","type":"trifecta","key":[3,1,7],"odds":20.5},{"id":"dfb59f6e-105f-4776-b019-fb54d808328f","type":"trifecta","key":[1,7,6],"odds":59.1},{"id":"e02f24c3-306b-4c6e-ab27-dc6b6dde489c","type":"trifecta","key":[8,3,9],"odds":241.1},{"id":"e075b94f-9d73-466d-9961-9535a04a7d7a","type":"trifecta","key":[3,5,6],"odds":152.9},{"id":"e087da35-a91f-4b04-b494-8558bd05eb8f","type":"trifecta","key":[2,5,8],"odds":225},{"id":"e167166f-3be2-4fe9-8a16-c18a70ecc79c","type":"trifecta","key":[4,5,1],"odds":232.6},{"id":"e18d58cb-da83-45d9-832f-3781c0e5e515","type":"trifecta","key":[7,9,3],"odds":130.4},{"id":"e29422a3-336d-4c2e-8296-18ff06f44f3c","type":"trifecta","key":[1,3,2],"odds":284.3},{"id":"e29b33f4-f52e-4299-8205-2d7d898ec9f9","type":"trifecta","key":[6,7,9],"odds":254.8},{"id":"e33fa859-33c4-4ec7-aa09-e6648d8590ab","type":"trifecta","key":[5,4,7],"odds":210.9},{"id":"e49f17b3-c24b-4f60-8a01-d75adc769a2f","type":"trifecta","key":[7,4,9],"odds":280},{"id":"e692e8b7-0ff1-4031-810e-44a90c06ec35","type":"trifecta","key":[3,6,8],"odds":229.6},{"id":"e7364ed9-6118-4170-976c-a902c10380ab","type":"trifecta","key":[9,4,7],"odds":288.6},{"id":"e7d3cd48-d196-4e45-9bf3-f1a12a569fae","type":"trifecta","key":[5,7,6],"odds":270.7},{"id":"e8e6b2a2-cd2e-4f3a-a193-087f9db097c0","type":"trifecta","key":[7,6,9],"odds":113.6},{"id":"e9b45893-4be7-4d6f-a7dd-3af8cdb60302","type":"trifecta","key":[4,2,7],"odds":215.2},{"id":"e9bd0850-746a-46df-9447-336fd0de514e","type":"trifecta","key":[1,4,5],"odds":283.3},{"id":"eaa0cfd5-bf6d-4c42-bdda-11eadf6d0377","type":"trifecta","key":[8,3,5],"odds":245},{"id":"eaf730ca-59a9-4b0e-9228-0fda2ec4f6fe","type":"trifecta","key":[1,4,2],"odds":101.8},{"id":"eb0279b6-69bd-4537-beed-17e9954517e6","type":"trifecta","key":[4,1,6],"odds":23.2},{"id":"eb62b8b4-8e03-428c-b39b-a66efdd6da46","type":"trifecta","key":[3,4,8],"odds":192.8},{"id":"ebafcaa1-4c28-46f3-8636-ed8868177a06","type":"trifecta","key":[8,3,4],"odds":227.1},{"id":"ebccb1d1-a7ba-4fda-acba-f521a4295b5b","type":"trifecta","key":[6,2,9],"odds":94.1},{"id":"ec5d3c2f-ebbf-4b0b-aa9d-34213ba7da27","type":"trifecta","key":[7,9,5],"odds":120.9},{"id":"ed15a63e-2e35-40b1-8320-e2d196968be0","type":"trifecta","key":[1,2,6],"odds":94.8},{"id":"ed8ff056-6b23-44b2-b679-3cb2f388469e","type":"trifecta","key":[5,4,2],"odds":213.8},{"id":"edb90bf5-e62c-4bff-ba1d-f27f0e96df88","type":"trifecta","key":[7,3,8],"odds":230.7},{"id":"ee6bc06f-c667-4b00-a185-9fdb12847905","type":"trifecta","key":[6,1,8],"odds":216.2},{"id":"ef117cb6-f283-4928-bbca-35e7d6a6bc42","type":"trifecta","key":[8,5,9],"odds":85.6},{"id":"ef338322-6b2f-4f0e-ba6b-f8dc0cc1f607","type":"trifecta","key":[7,5,4],"odds":180.5},{"id":"ef33bc09-4a83-4571-a0c2-0c2e8b9294cd","type":"trifecta","key":[5,6,8],"odds":86.5},{"id":"f100fed3-0fb0-4047-8292-41d6cbe80dfe","type":"trifecta","key":[1,3,9],"odds":173.3},{"id":"f1ac7613-7ee5-448b-a5d0-62b4b828cd7a","type":"trifecta","key":[4,9,6],"odds":229.5},{"id":"f1e98c96-817d-4521-a3a2-ec7e7f76ebfd","type":"trifecta","key":[1,7,8],"odds":173},{"id":"f384f4fa-92a2-4426-bc8e-3de3dbea9bca","type":"trifecta","key":[3,9,6],"odds":188.5},{"id":"f3a52181-381b-45e8-8ffa-58c091f58025","type":"trifecta","key":[2,5,3],"odds":10.9},{"id":"f3c0864b-da63-4762-a2f7-384850ee07b0","type":"trifecta","key":[5,7,9],"odds":54.7},{"id":"f3f2c638-73f2-4db0-a88a-4a00b2efefd7","type":"trifecta","key":[8,4,5],"odds":40.7},{"id":"f3f61a8e-de04-43d1-93e7-4e993fb510ca","type":"trifecta","key":[1,7,4],"odds":236.4},{"id":"f516198c-3d85-4182-ba72-d4291cb85a77","type":"trifecta","key":[8,1,4],"odds":260.3},{"id":"f51c2b41-b67f-4cbe-80ea-0652faf96ffd","type":"trifecta","key":[1,2,4],"odds":290.8},{"id":"f5913f0e-6634-47a2-a7c1-9e0b59d5a82a","type":"trifecta","key":[6,8,7],"odds":198.3},{"id":"f7afaf73-e72d-4b2f-bc16-741004b6aa86","type":"trifecta","key":[9,6,3],"odds":292.5},{"id":"f7b17e01-64cb-4c49-8cb4-ad5ba24e5746","type":"trifecta","key":[4,5,6],"odds":237.6},{"id":"f7eac99a-4e34-425f-98d8-af4d38f00c34","type":"trifecta","key":[8,9,3],"odds":259.6},{"id":"f820127c-11b1-4a48-b0e1-6c5efe52d598","type":"trifecta","key":[6,8,3],"odds":200.6},{"id":"f86388c6-ec9d-4638-b111-a432c4edb1ed","type":"trifecta","key":[3,8,7],"odds":213.6},{"id":"f887fbcc-d88f-4c56-a250-bf92f020847a","type":"trifecta","key":[9,3,5],"odds":31.7},{"id":"f920379e-20a6-4a65-804c-162cd2fb3862","type":"trifecta","key":[3,9,7],"odds":174.7},{"id":"f972d039-08b7-4856-b09a-fd60fe53e69d","type":"trifecta","key":[4,6,1],"odds":139.7},{"id":"f9c15cad-c2e7-4fda-bf2b-071e3b6a0be2","type":"trifecta","key":[4,1,7],"odds":292.4},{"id":"fa412650-c9e2-43a7-ad76-b017f231599e","type":"trifecta","key":[4,6,9],"odds":150.7},{"id":"fa5c7991-54a0-41e0-872c-f45099049c17","type":"trifecta","key":[2,5,1],"odds":168},{"id":"fa65fd00-27ff-48d7-9a96-6d6dcc00235f","type":"trifecta","key":[2,7,6],"odds":144},{"id":"fa904239-babf-40e0-99bd-127c742fee1b","type":"trifecta","key":[7,2,6],"odds":29.9},{"id":"fa95ed87-96a9-472b-8001-e0847097b522","type":"trifecta","key":[1,6,2],"odds":276.6},{"id":"fb6db4fd-80ee-44f8-88d7-9cf76e6f1f57","type":"trifecta","key":[1,3,5],"odds":66.7},{"id":"fbfb4d1b-5229-4948-9abf-87e1c8933ed8","type":"trifecta","key":[3,4,9],"odds":106.8},{"id":"fc26285e-9f4c-4cc7-b338-9b57a75d424e","type":"trifecta","key":[2,4,8],"odds":140.3},{"id":"fc4b82a5-2c4e-4975-8442-c9bc3ed58a33","type":"trifecta","key":[7,9,1],"odds":30.1},{"id":"fcbc7f18-3619-4d47-85b8-904d3e89aac4","type":"trifecta","key":[1,6,9],"odds":209.3},{"id":"fed2f7e5-aac1-496b-8212-d3c94fbfcc46","type":"trifecta","key":[2,9,7],"odds":23.9},{"id":"fee76fee-779f-4b41-8be8-d80ec83b49e0","type":"trifecta","key":[6,1,9],"odds":62.4},{"id":"ff446cdc-f937-4280-bf49-4720fd1bd2d6","type":"trifecta","key":[9,6,5],"odds":250.7},{"id":"ffb959c0-6dbe-4d57-a290-09f3b355c0ef","type":"trifecta","key":[4,1,5],"odds":21.2},{"id":"fff2c34b-2ed5-40bf-bf40-56eb520690f5","type":"trifecta","key":[9,8,2],"odds":137.2}]}