{"id":"f25453fe-a5a8-4006-bcf1-d0e87db4829b","name":"サイバーエージェント記念カップ","image":"/assets/images/races/017.jpg","startAt":"2024-02-07T03:20:00.000Z","closeAt":"2024-02-07T03:20:00.000Z","entries":[{"id":"930cb8c8-f70f-4860-9b49-5222dbb8ece1","number":1,"player":{"id":"2cac85e1-4794-4f5a-ab0e-f3c28ff5b24a","name":"川合正治","shortName":"川合正","image":"/assets/images/players/019.jpg"},"predictionMark":"","first":10,"second":3,"third":7,"others":10,"rockWin":10,"scissorsWin":0,"paperWin":0,"firstRate":33.33333333333333,"thirdRate":66.66666666666667,"comment":"自分の癖が見えてきた"},{"id":"e4e61336-93e9-4673-8699-47ab4109a910","number":2,"player":{"id":"00594237-c10d-4707-b4eb-9a15cd7ea29a","name":"徳永志乃","shortName":"徳永志","image":"/assets/images/players/004.jpg"},"predictionMark":"","first":2,"second":8,"third":6,"others":10,"rockWin":1,"scissorsWin":0,"paperWin":1,"firstRate":7.6923076923076925,"thirdRate":61.53846153846154,"comment":"子供時代は連戦連勝"},{"id":"e3007022-cd3d-46a9-9d04-7a9a8a8f3c99","number":3,"player":{"id":"facfa8b4-2a7b-444f-9a71-34e2b34f9161","name":"前川洋二","shortName":"前川洋","image":"/assets/images/players/005.jpg"},"predictionMark":"","first":8,"second":5,"third":5,"others":10,"rockWin":3,"scissorsWin":4,"paperWin":1,"firstRate":28.57142857142857,"thirdRate":64.28571428571428,"comment":"おみくじ大吉でした"},{"id":"f31bd32d-3a10-47ca-8f65-ba22de575503","number":4,"player":{"id":"c030b350-f16c-4862-bedf-14e4d8dd4d76","name":"浜崎真佳奈","shortName":"浜崎真","image":"/assets/images/players/010.jpg"},"predictionMark":"","first":6,"second":4,"third":7,"others":0,"rockWin":4,"scissorsWin":0,"paperWin":2,"firstRate":35.294117647058826,"thirdRate":100,"comment":"相手の研究は完璧"},{"id":"e395f658-56d2-4163-a4a8-e4a0c920ce1d","number":5,"player":{"id":"d8400a7f-8194-497a-a7f9-de2f3785c29d","name":"古沢瑞稀","shortName":"古沢瑞","image":"/assets/images/players/007.jpg"},"predictionMark":"△","first":9,"second":5,"third":10,"others":9,"rockWin":6,"scissorsWin":1,"paperWin":2,"firstRate":27.27272727272727,"thirdRate":72.72727272727273,"comment":"おみくじ大吉でした"},{"id":"6007dc7c-2e25-442f-855e-1c089605ad7e","number":6,"player":{"id":"b82ebecd-715c-4d46-b6df-029c869ffc59","name":"川田時夫","shortName":"川田時","image":"/assets/images/players/002.jpg"},"predictionMark":"×","first":1,"second":6,"third":3,"others":5,"rockWin":1,"scissorsWin":0,"paperWin":0,"firstRate":6.666666666666667,"thirdRate":66.66666666666667,"comment":"開いた手の大きさなら負けません"},{"id":"9c85793e-3693-45d7-b1de-87e306353f01","number":7,"player":{"id":"14b44dba-3601-422b-80ec-38ce9c2c1a4e","name":"村山啓一","shortName":"村山啓","image":"/assets/images/players/006.jpg"},"predictionMark":"○","first":2,"second":6,"third":0,"others":8,"rockWin":2,"scissorsWin":0,"paperWin":0,"firstRate":12.5,"thirdRate":50,"comment":"なんかいけそう"},{"id":"8a971299-978e-479b-b0e3-a811cf9b5852","number":8,"player":{"id":"cbe93e1e-e71a-4774-8f2d-ab0fa6236c39","name":"寺西陽子","shortName":"寺西陽","image":"/assets/images/players/001.jpg"},"predictionMark":"","first":0,"second":5,"third":7,"others":9,"rockWin":0,"scissorsWin":0,"paperWin":0,"firstRate":0,"thirdRate":57.14285714285714,"comment":"今日も朝練してきました"},{"id":"15249fad-5087-4ef2-ae47-96a9f7d8416d","number":9,"player":{"id":"b6189e85-4e87-4412-bada-b12aba777732","name":"清水小雪","shortName":"清水小","image":"/assets/images/players/020.jpg"},"predictionMark":"◎","first":6,"second":3,"third":1,"others":1,"rockWin":6,"scissorsWin":0,"paperWin":0,"firstRate":54.54545454545454,"thirdRate":90.9090909090909,"comment":"子供時代は連戦連勝"}],"trifectaOdds":[{"id":"00e8ce55-aba9-441a-b7b2-059053ee6a5b","type":"trifecta","key":[3,6,4],"odds":186},{"id":"014ec8e7-9b0c-4bb0-86e4-e35858de7fab","type":"trifecta","key":[6,3,1],"odds":210.3},{"id":"028018b3-73f1-4780-93a6-e4c667ff8fa6","type":"trifecta","key":[4,9,7],"odds":153.9},{"id":"028759a1-17da-4ccf-b5d6-d1d37ebde9c3","type":"trifecta","key":[4,6,9],"odds":237},{"id":"03a41ca7-a0f0-47a3-89d5-5a04a4c9ba33","type":"trifecta","key":[1,8,3],"odds":122.4},{"id":"03ab2d42-2c5d-43d2-8ba7-a7acc7574f0f","type":"trifecta","key":[2,4,5],"odds":200.1},{"id":"03bd47ff-ac84-4b45-82f8-ace0a1bc0e04","type":"trifecta","key":[4,1,9],"odds":191},{"id":"050b6aa3-ab28-49ac-bb1f-d24188dfba7b","type":"trifecta","key":[4,8,7],"odds":274.6},{"id":"0541a196-a697-4c31-95d2-b69e170ae2f5","type":"trifecta","key":[2,9,5],"odds":110.7},{"id":"0548c7dd-34c7-472e-a267-ddf76a08f0ea","type":"trifecta","key":[8,1,5],"odds":69.2},{"id":"056a9c7c-b431-4e8d-b24a-b5c69426694a","type":"trifecta","key":[3,6,8],"odds":238.1},{"id":"05c6996a-9214-41ba-a254-11f87d1fdd2d","type":"trifecta","key":[2,5,9],"odds":114.5},{"id":"063beb28-75bc-497f-95d6-6788ffd74980","type":"trifecta","key":[9,2,7],"odds":118.6},{"id":"06dac10f-70f1-4bfd-93ac-a2b829f9f0be","type":"trifecta","key":[8,6,7],"odds":28.6},{"id":"06fba81a-aa39-4771-89ef-c9505532b606","type":"trifecta","key":[1,6,5],"odds":34.6},{"id":"08f7139f-1379-419c-ad46-3fd1264b00aa","type":"trifecta","key":[2,1,5],"odds":293.9},{"id":"0a3e3374-f5bb-4258-ba33-a39300c35220","type":"trifecta","key":[3,6,9],"odds":5.3},{"id":"0aefcb8e-7b3c-478d-a3f5-3b2c9e5b8c5f","type":"trifecta","key":[2,5,4],"odds":195.6},{"id":"0b4ae3e9-e584-474f-8b50-962bae814d0f","type":"trifecta","key":[8,6,9],"odds":53.8},{"id":"0b7dbace-6885-4b91-856f-86e269123fe8","type":"trifecta","key":[9,5,4],"odds":180.7},{"id":"0c041aec-e1ff-4bf1-b70b-3b7ec05a0370","type":"trifecta","key":[2,7,3],"odds":86.2},{"id":"0c621861-3d70-430c-9765-4c9c7df7dc64","type":"trifecta","key":[7,3,6],"odds":60.3},{"id":"0d91a1c7-bc0c-4aaa-ade1-96b59749e106","type":"trifecta","key":[8,1,9],"odds":279.6},{"id":"0df120e7-09cf-4d14-82a9-379b80dc8e4c","type":"trifecta","key":[7,4,1],"odds":2.9},{"id":"0e253519-fce1-44ba-9e63-aafcffede4fb","type":"trifecta","key":[4,7,2],"odds":152.1},{"id":"0f1af9e1-fc6c-415b-bfaa-83d589895128","type":"trifecta","key":[5,4,8],"odds":132},{"id":"1007339d-5e3f-4c4f-bf58-8b33be04f301","type":"trifecta","key":[9,7,6],"odds":187.3},{"id":"103f51b0-bdd0-4c99-b2fc-b5f077ec5284","type":"trifecta","key":[5,1,6],"odds":291.6},{"id":"10690834-be0d-4d7e-a475-e965263a096d","type":"trifecta","key":[4,7,6],"odds":54.2},{"id":"10dad05d-65d7-4f6e-a4fb-72cd5e9c09ae","type":"trifecta","key":[9,3,8],"odds":83.6},{"id":"113662ec-da3b-446b-b9bf-adb41fb7c836","type":"trifecta","key":[6,9,8],"odds":4.8},{"id":"12668599-7418-43c5-a7f1-d88bdf1f255c","type":"trifecta","key":[6,2,8],"odds":93.6},{"id":"12bb2f06-8a14-4729-bf01-0c83b491c264","type":"trifecta","key":[9,7,3],"odds":24.4},{"id":"13e6c72c-9e5c-48df-aa4b-74066d439271","type":"trifecta","key":[7,8,1],"odds":107},{"id":"14ec4536-6bcb-491a-a1b2-7c269708387a","type":"trifecta","key":[9,4,7],"odds":296.9},{"id":"15db350e-1b5b-4e73-83cf-90ab96169a73","type":"trifecta","key":[5,3,1],"odds":135.5},{"id":"160633a5-01a5-4d18-8961-f211cd51990e","type":"trifecta","key":[4,9,8],"odds":193.4},{"id":"165e0a2e-cf7e-438f-bd27-ebef75ec8793","type":"trifecta","key":[7,9,4],"odds":27.5},{"id":"17978f9d-c4f2-4e9c-b550-9ce90e7709c5","type":"trifecta","key":[8,9,4],"odds":96.5},{"id":"1797d335-e272-4b45-8a49-811c49a77e6f","type":"trifecta","key":[8,9,2],"odds":144.3},{"id":"17a5ba5b-2ae3-456b-802f-fc8f2fdbd336","type":"trifecta","key":[2,4,8],"odds":108.9},{"id":"1816109c-02e8-4f3b-9d37-ad799f584201","type":"trifecta","key":[2,6,7],"odds":217},{"id":"181e50fa-b980-43a3-a804-cdc8440693a4","type":"trifecta","key":[1,4,5],"odds":169.2},{"id":"1859d68c-4361-472d-b48a-5877853a1f1a","type":"trifecta","key":[3,4,1],"odds":166.3},{"id":"19aa6556-2622-47ca-aadb-932317cae2e7","type":"trifecta","key":[8,4,9],"odds":24.6},{"id":"1a367a47-0f04-4879-a451-cefada4a9cc2","type":"trifecta","key":[4,3,5],"odds":261.2},{"id":"1ad49297-3db5-4323-9606-3024f4b81881","type":"trifecta","key":[2,3,6],"odds":23.8},{"id":"1cffe249-cd3a-4f58-aaea-499c4a546c74","type":"trifecta","key":[6,7,1],"odds":97.1},{"id":"1d555f10-2f0c-4e2c-9913-5b86acf9eb0b","type":"trifecta","key":[4,9,2],"odds":256.2},{"id":"1d7ef0a1-3283-4ec0-b932-ec47da393ab9","type":"trifecta","key":[6,4,3],"odds":273},{"id":"1e9f04ec-169b-4d7e-bf42-4b56358cbe54","type":"trifecta","key":[3,6,2],"odds":80.5},{"id":"1f295bbe-b799-497b-a488-aa15961ceb72","type":"trifecta","key":[9,6,1],"odds":215.4},{"id":"1f41b913-7fae-4e6a-b27f-801ca8a6bc03","type":"trifecta","key":[7,6,2],"odds":140.3},{"id":"1fb5ece3-d507-4887-b277-f33db147bbe5","type":"trifecta","key":[1,2,8],"odds":221.9},{"id":"1ff3d7ba-b288-4046-bd15-4ffbdb8bd595","type":"trifecta","key":[3,9,4],"odds":205.8},{"id":"20896f19-7e68-4e5b-9150-c6ee1037a434","type":"trifecta","key":[2,4,1],"odds":116.1},{"id":"20973761-854f-4026-9312-133a5515e210","type":"trifecta","key":[7,6,1],"odds":172.4},{"id":"20d78b84-1edd-48ba-ba74-5a03a8dbea41","type":"trifecta","key":[8,6,1],"odds":107.1},{"id":"2106ef23-fa7a-4e4e-b3f2-6d7a55394863","type":"trifecta","key":[8,4,6],"odds":228},{"id":"211b31fc-14aa-4881-a537-989143020ede","type":"trifecta","key":[7,4,2],"odds":262},{"id":"212f3896-0cb8-488c-8a77-ad64f2e6284b","type":"trifecta","key":[4,1,2],"odds":114.3},{"id":"21a06420-dee2-4ae6-8a2b-709339580468","type":"trifecta","key":[6,7,5],"odds":204.6},{"id":"21c036fb-5412-40f7-8028-849e013f7071","type":"trifecta","key":[7,5,9],"odds":214.5},{"id":"2283872a-b0b5-4970-b78d-51a1acaed8a3","type":"trifecta","key":[1,3,9],"odds":116.5},{"id":"243b1e75-c16e-43de-9d6c-f4d8a40aaca7","type":"trifecta","key":[4,2,3],"odds":17.1},{"id":"2453cf36-2f4a-45fa-bb56-40c480712c94","type":"trifecta","key":[7,9,1],"odds":84.3},{"id":"25c34259-bd93-4014-a0d8-8ce38626fecc","type":"trifecta","key":[4,2,1],"odds":282.9},{"id":"25d0a785-071d-4044-b42c-96aa8fc101d5","type":"trifecta","key":[5,7,3],"odds":151.7},{"id":"267d2745-f8f5-4448-8bc4-d9b39a6884d6","type":"trifecta","key":[6,7,9],"odds":186.1},{"id":"2689fad8-a8dd-4283-a18d-c4f3e17923c2","type":"trifecta","key":[9,8,3],"odds":138.6},{"id":"26b688f9-a803-4db3-b790-236fd390b722","type":"trifecta","key":[3,7,9],"odds":194.4},{"id":"26e03545-0026-4b77-9beb-0b227fe67220","type":"trifecta","key":[1,8,2],"odds":70.2},{"id":"2710eebb-6178-4356-9fe5-cb4e6565f976","type":"trifecta","key":[7,6,9],"odds":230.3},{"id":"27c0151f-30e4-4132-a2cf-62c7afd21631","type":"trifecta","key":[7,3,8],"odds":228.2},{"id":"27ebaef1-7d55-4251-a239-0c3f20fb653a","type":"trifecta","key":[3,8,1],"odds":120.4},{"id":"29593ae9-0790-4a7e-be51-c25f41d3722a","type":"trifecta","key":[5,6,8],"odds":166.7},{"id":"29cbdee1-105f-49a6-9c26-0c25d24c1e52","type":"trifecta","key":[7,4,6],"odds":293.4},{"id":"2a3631b9-d755-4d7a-bd46-6572f72999ec","type":"trifecta","key":[7,1,4],"odds":3.3},{"id":"2a40a667-55cb-4f0a-9a71-ac6cbe265792","type":"trifecta","key":[3,9,5],"odds":134},{"id":"2a4ddbc4-fab3-4d45-a543-a9ad6da3010a","type":"trifecta","key":[4,1,6],"odds":58.9},{"id":"2bb5d0fd-8e0d-4cad-b2cd-b28ae0045230","type":"trifecta","key":[2,7,8],"odds":192.3},{"id":"2bd37683-60ca-4d0f-8cd3-1451b74ef9ee","type":"trifecta","key":[7,8,4],"odds":290.8},{"id":"2c302129-3d89-4316-b373-a9d97eb764e9","type":"trifecta","key":[4,7,8],"odds":90.3},{"id":"2c5113d3-5b27-4d6d-a430-1ecb4fb27f2f","type":"trifecta","key":[9,1,4],"odds":150.5},{"id":"2cbabfb7-4f7b-4972-b9df-21e7b547f04f","type":"trifecta","key":[1,5,8],"odds":215},{"id":"2cd334e3-95f1-42fb-92b4-dc4c5f006e1c","type":"trifecta","key":[7,1,5],"odds":4.8},{"id":"2d6e709f-9ba3-4659-a955-0354a1727605","type":"trifecta","key":[2,7,4],"odds":230.3},{"id":"2d8558d2-0315-40d0-b4e1-e53f42e11c70","type":"trifecta","key":[7,8,3],"odds":100.8},{"id":"2da64f85-4d9a-4fc8-944e-5e7519a6023d","type":"trifecta","key":[3,4,9],"odds":274.8},{"id":"2de1664d-2448-4393-9984-20663ee924e7","type":"trifecta","key":[1,5,7],"odds":181.3},{"id":"2e6a9b99-aa16-4671-9580-181db8204719","type":"trifecta","key":[5,1,9],"odds":179.3},{"id":"2e87eb96-98fb-4f70-a7c3-fa316810023c","type":"trifecta","key":[4,8,6],"odds":10.8},{"id":"2f24e311-2427-4f4f-bd27-e583fea21308","type":"trifecta","key":[4,5,3],"odds":93.6},{"id":"2fd2bef1-9860-4f85-a763-e8004ff001ba","type":"trifecta","key":[3,8,7],"odds":277.8},{"id":"30620885-ed72-47aa-96b9-6e6680ea9ceb","type":"trifecta","key":[5,9,3],"odds":170.2},{"id":"308b7a73-ecfb-4802-805a-7e6d7883a36d","type":"trifecta","key":[1,3,8],"odds":34.2},{"id":"30a18d5d-a7ef-4c45-b6cd-46f80acef923","type":"trifecta","key":[5,9,1],"odds":150},{"id":"30a32b15-0fb7-4215-a662-d4092e347d95","type":"trifecta","key":[4,2,5],"odds":88.9},{"id":"30a97c21-4eb6-4843-be66-f281679a220e","type":"trifecta","key":[5,3,9],"odds":227},{"id":"30be6514-0c27-42c7-bc2e-d37be57fcff5","type":"trifecta","key":[3,5,9],"odds":39.8},{"id":"30fb7cb9-79e3-4d33-8887-3b678ffbca60","type":"trifecta","key":[4,2,8],"odds":278.1},{"id":"31d3e99c-2442-4592-bfac-930f9c5bea57","type":"trifecta","key":[5,7,2],"odds":132.2},{"id":"3206a9f8-e20e-4b60-bef6-568a2478951e","type":"trifecta","key":[2,8,1],"odds":256.5},{"id":"32614cf1-b6f5-4ae4-b843-9fafc5f70f06","type":"trifecta","key":[3,1,5],"odds":44.6},{"id":"3399214a-f08a-45a5-9fa0-b03585b6b914","type":"trifecta","key":[5,6,7],"odds":48.2},{"id":"341309f6-9981-41bf-a252-c24f873921e7","type":"trifecta","key":[5,8,7],"odds":59.4},{"id":"37317b16-cb0f-4238-a85b-da7f75de1754","type":"trifecta","key":[9,6,3],"odds":266.3},{"id":"378bf505-c9c4-4c99-96b3-b217f16ba734","type":"trifecta","key":[9,4,8],"odds":106.4},{"id":"37ac2060-2461-4334-9cc5-e5e1c1377d34","type":"trifecta","key":[9,3,7],"odds":19.3},{"id":"37f61a42-f2c9-4102-b5ec-cd5edd185f4d","type":"trifecta","key":[2,5,8],"odds":280.5},{"id":"3847d0f6-35e4-4c84-80cd-139b25ed5f5a","type":"trifecta","key":[9,4,3],"odds":241.5},{"id":"38c1c097-3087-4237-9724-26c03f8da562","type":"trifecta","key":[9,2,3],"odds":148.2},{"id":"394c917b-cdc2-4fd5-8b1a-f2a9b500e2fd","type":"trifecta","key":[1,5,4],"odds":166},{"id":"3a1974c5-29ef-43c7-82ae-36f880d66c54","type":"trifecta","key":[8,9,7],"odds":26.8},{"id":"3c034c6e-74c1-4e94-bd33-e2c26641b1e3","type":"trifecta","key":[7,9,5],"odds":18.3},{"id":"3c3d9e39-a3bc-4cf4-bde4-6ce376eacc8a","type":"trifecta","key":[8,9,1],"odds":275.4},{"id":"3cdec50c-f44c-4d2c-9d67-a867b03c9f30","type":"trifecta","key":[6,5,1],"odds":64},{"id":"3d43e5b9-cfac-478f-9421-896efabfc7e7","type":"trifecta","key":[1,4,2],"odds":7.8},{"id":"3e08b7d7-3aa4-416d-a84a-ac7be408624e","type":"trifecta","key":[2,7,1],"odds":178.7},{"id":"3e09894a-4b84-4ea2-a92a-d65268d0af2b","type":"trifecta","key":[5,9,7],"odds":189.1},{"id":"3e512190-b144-44e7-a737-82bac2af0192","type":"trifecta","key":[9,6,5],"odds":131.5},{"id":"3e65c4ee-c42f-4153-b498-8690c47c5231","type":"trifecta","key":[7,2,3],"odds":144.3},{"id":"3e853af7-2864-4080-8545-640261418654","type":"trifecta","key":[9,7,8],"odds":297.4},{"id":"3efdec4a-044f-410c-a04c-67f64aed0ff0","type":"trifecta","key":[8,4,5],"odds":142.5},{"id":"3f2ce3fe-5f78-42ea-931f-3f37995e8d72","type":"trifecta","key":[5,8,4],"odds":105.8},{"id":"3f2e78fb-8530-4682-9ca6-8772a0b002b9","type":"trifecta","key":[7,3,9],"odds":106.9},{"id":"3f8c05ae-9eb0-4c42-9d19-4aacab4e0be3","type":"trifecta","key":[6,9,1],"odds":184.2},{"id":"3f9c8a70-faf1-4464-8e12-013cbfdb645f","type":"trifecta","key":[7,2,1],"odds":166.2},{"id":"3fd1dfb8-3872-4205-8be2-9858d66df7f8","type":"trifecta","key":[6,4,2],"odds":192.5},{"id":"41ce2662-69fd-4f20-8962-5396a70ac784","type":"trifecta","key":[3,1,8],"odds":196.8},{"id":"421f04a7-d06f-49b4-8409-6422b4b04135","type":"trifecta","key":[8,7,2],"odds":298.1},{"id":"425a58a0-f61f-4045-9227-1f2877e7839b","type":"trifecta","key":[3,8,9],"odds":26},{"id":"4345ac72-6493-48ad-b1b2-cf21d8b38195","type":"trifecta","key":[3,4,6],"odds":288.3},{"id":"4347f486-9f8b-4f03-aed9-af846fb8dc18","type":"trifecta","key":[1,7,2],"odds":45.3},{"id":"4400566d-7aba-4a2d-a55f-fee58c6e83a3","type":"trifecta","key":[9,2,4],"odds":42.7},{"id":"44440a56-7eb5-4c46-a0fc-203fd504336f","type":"trifecta","key":[9,3,4],"odds":108.6},{"id":"445748ec-fb41-4b3d-a390-0f32f2ce0a2f","type":"trifecta","key":[9,6,7],"odds":176.7},{"id":"447705d4-b6c5-4f64-964e-b66539c6a249","type":"trifecta","key":[9,4,5],"odds":239.7},{"id":"47a8cea9-14a6-4aad-b003-e3e3e53e2a22","type":"trifecta","key":[5,8,3],"odds":198.3},{"id":"47b64641-346d-4691-976f-4a34809419e2","type":"trifecta","key":[7,5,6],"odds":155.4},{"id":"4824baf5-a8ca-4b56-94cf-ab07d80f5641","type":"trifecta","key":[3,1,2],"odds":194.1},{"id":"48e3af6c-f518-4726-9dee-7b726b078def","type":"trifecta","key":[7,1,6],"odds":289.1},{"id":"4936a3d2-d931-41dc-8209-ce6311965333","type":"trifecta","key":[6,8,2],"odds":20},{"id":"4c00fab4-a724-4520-9733-fd29a812c531","type":"trifecta","key":[7,1,2],"odds":259.9},{"id":"4c09bdac-7db9-49ce-b9e2-1db7da79372b","type":"trifecta","key":[2,8,6],"odds":216.9},{"id":"4c7eb1ee-86ed-4af9-805d-1b52d0eb5736","type":"trifecta","key":[3,5,7],"odds":212.5},{"id":"4d314486-a8d4-4bdf-8b7e-1b7b794f647d","type":"trifecta","key":[8,9,3],"odds":134.3},{"id":"4daf8623-4288-47e0-a1c9-3521a102025b","type":"trifecta","key":[4,3,8],"odds":26.8},{"id":"4e0a31fd-18d7-4033-bd8c-fbb4c1a61dd8","type":"trifecta","key":[8,4,2],"odds":46.5},{"id":"4e6566eb-3ee5-43c1-9dbe-afea3cfc3a84","type":"trifecta","key":[5,8,2],"odds":177.1},{"id":"4ee1a4f0-fe24-4926-9447-5d4bbaee9ba0","type":"trifecta","key":[1,5,2],"odds":179.8},{"id":"4f0a3bae-7d82-432e-83b2-cc673260806a","type":"trifecta","key":[9,4,1],"odds":147.7},{"id":"4f250fc2-36eb-4a45-9743-1042517f93cf","type":"trifecta","key":[1,8,7],"odds":137.1},{"id":"4f416844-1097-45b1-a783-03968b7d8558","type":"trifecta","key":[5,6,2],"odds":297.1},{"id":"50523ca0-a61e-4afc-b445-4895a9d3730d","type":"trifecta","key":[1,5,9],"odds":118.6},{"id":"50dd0af0-2764-4f53-bcd3-760714b07659","type":"trifecta","key":[6,1,5],"odds":109.6},{"id":"52cd1077-8d18-48df-b04e-48b319b856fd","type":"trifecta","key":[5,4,6],"odds":69.1},{"id":"5327fe85-f3a3-4038-a18e-bf25748a2486","type":"trifecta","key":[4,3,7],"odds":12.1},{"id":"532c35af-5a4d-4bb1-8427-94d750be8237","type":"trifecta","key":[7,4,3],"odds":228.8},{"id":"542c83a1-a2c4-473e-877b-d24fccfe21cd","type":"trifecta","key":[4,9,3],"odds":255.9},{"id":"56ec1bc5-fb24-4545-8246-f5c6ec48df97","type":"trifecta","key":[9,1,2],"odds":37.6},{"id":"57359b22-77dc-457b-aad3-fd741b753243","type":"trifecta","key":[7,6,3],"odds":12.9},{"id":"57b1c9bd-f0a9-42fe-bcfb-72afa98a9027","type":"trifecta","key":[1,3,6],"odds":181.1},{"id":"58201154-4979-4dff-85d4-5271f77e2024","type":"trifecta","key":[5,7,6],"odds":101.8},{"id":"5839d325-ad35-431d-b551-778ad00ad6d5","type":"trifecta","key":[5,2,6],"odds":247.8},{"id":"589e1730-eef8-491f-afef-acb56a4d9914","type":"trifecta","key":[6,2,3],"odds":224.9},{"id":"592014ff-85fc-4bc2-8b30-45b94ed3c285","type":"trifecta","key":[3,5,1],"odds":222.1},{"id":"5aef7eaa-51d3-4226-8297-e827d1b25d82","type":"trifecta","key":[2,1,9],"odds":131.7},{"id":"5b1280f2-83cb-4f0c-81ac-d201c04bd57c","type":"trifecta","key":[3,2,9],"odds":247.5},{"id":"5b3d3173-5b60-4c46-b13e-5e7d9e09be38","type":"trifecta","key":[9,5,2],"odds":180.9},{"id":"5b4859bf-0f1b-4f85-bdad-516e741ea413","type":"trifecta","key":[2,7,6],"odds":297},{"id":"5ba0d293-beb0-41f7-9bcf-38d212b8cb54","type":"trifecta","key":[7,2,5],"odds":238.8},{"id":"5c6a4da5-b2d6-4af5-9652-22c716bdae58","type":"trifecta","key":[6,4,1],"odds":125.4},{"id":"5ca1bfc1-81e5-4e79-8ff5-16cb9715749e","type":"trifecta","key":[1,3,2],"odds":23.7},{"id":"5cae1bce-e521-4af2-9f1f-7b0ef7d6b072","type":"trifecta","key":[6,8,9],"odds":241.7},{"id":"5ce6e7c5-5b4a-481f-96f5-2f74ae9446f9","type":"trifecta","key":[2,8,3],"odds":116.1},{"id":"5d109ce5-f2ca-406d-84f8-dec36df01634","type":"trifecta","key":[1,9,4],"odds":103.7},{"id":"5d269f6a-ef2e-4558-b9e4-cdaf6b842e0e","type":"trifecta","key":[5,6,1],"odds":29.2},{"id":"5d758fca-cdf8-4fc1-82b5-1aff6458e803","type":"trifecta","key":[1,4,7],"odds":271.7},{"id":"5e2e948c-48f8-4f6f-87c9-085b6ce51d04","type":"trifecta","key":[9,3,6],"odds":61.4},{"id":"5e51cc29-27d5-4027-bd3a-d6d86b36800c","type":"trifecta","key":[7,1,9],"odds":208.1},{"id":"5ebee090-4419-482f-ab41-a1f9a48e6a72","type":"trifecta","key":[2,9,3],"odds":289.1},{"id":"5ed01297-14e9-44d1-8a1c-d87bed6a591c","type":"trifecta","key":[6,2,1],"odds":115.1},{"id":"5f810587-1f1b-4eda-99b2-e65b7cb01e61","type":"trifecta","key":[1,2,6],"odds":225.8},{"id":"5faffc4c-3e38-455a-b04b-ea370805ac85","type":"trifecta","key":[1,7,5],"odds":53.2},{"id":"5fd2ef7f-06ed-4302-b389-80bd1e8bf506","type":"trifecta","key":[2,6,5],"odds":130.3},{"id":"5fe304a4-f0b5-4b2f-a7f3-6f0921659d9e","type":"trifecta","key":[7,2,6],"odds":173.1},{"id":"60b8dd04-7ea6-4a09-9246-62b32f2c93ef","type":"trifecta","key":[5,7,9],"odds":231.1},{"id":"616674fe-1239-4a1e-a389-74d1d39feadd","type":"trifecta","key":[4,3,2],"odds":23.3},{"id":"61a892cd-149d-4668-8e6d-45c635311eb1","type":"trifecta","key":[7,8,9],"odds":178.3},{"id":"61b0ce13-d631-4570-919f-56cd4376b9ba","type":"trifecta","key":[2,5,6],"odds":44.9},{"id":"61eb350b-2345-4b0f-9cbc-d082202b2c36","type":"trifecta","key":[9,3,2],"odds":155},{"id":"6269f7e8-e027-49de-8dfc-107918b56595","type":"trifecta","key":[8,2,3],"odds":186.5},{"id":"6299cf53-1369-4dae-b8c7-26f060a6f347","type":"trifecta","key":[2,5,7],"odds":269.6},{"id":"6314cdaf-2b7c-4426-97b8-88b4a2493ff8","type":"trifecta","key":[8,2,5],"odds":273},{"id":"635f55a8-4d04-423e-96d3-c5415dd3926d","type":"trifecta","key":[9,8,2],"odds":168.3},{"id":"6395d198-3950-4e9e-86cb-1bcab7c2deac","type":"trifecta","key":[8,3,6],"odds":293.5},{"id":"63ab7174-75f1-4a9d-883e-072ca545bd9a","type":"trifecta","key":[6,2,7],"odds":62.3},{"id":"63c5c2e8-c05b-4f1c-8ba2-ea56a0ef4447","type":"trifecta","key":[6,2,9],"odds":110.9},{"id":"63e0725c-797e-403d-b52e-fdf1fe7e3dc0","type":"trifecta","key":[5,2,9],"odds":16.1},{"id":"642117b6-40cf-4110-9818-c71e58c0c4e1","type":"trifecta","key":[1,9,8],"odds":72.7},{"id":"651947e3-7b4a-4f0d-816c-9920c1375d7d","type":"trifecta","key":[9,1,8],"odds":115.5},{"id":"654a32b3-e9c9-4cc3-94b5-974b8d786170","type":"trifecta","key":[5,4,3],"odds":221.2},{"id":"6573cd4f-7cee-46e3-9515-24fb621a0b48","type":"trifecta","key":[3,2,8],"odds":289.2},{"id":"65fe121c-1bf2-481d-a63f-4ab130214015","type":"trifecta","key":[7,5,8],"odds":249.9},{"id":"66172c5d-76d9-4d07-b70e-2af1f7bed10a","type":"trifecta","key":[3,2,6],"odds":244},{"id":"66578dc6-c62f-4bbf-9daf-4b7f4f6cd918","type":"trifecta","key":[2,6,1],"odds":140.9},{"id":"66ff7ad3-ff2e-48ad-b14b-23427fdd1742","type":"trifecta","key":[8,7,9],"odds":166},{"id":"672b25d0-fe49-488b-bfb1-7daa793e2e86","type":"trifecta","key":[6,9,7],"odds":216.8},{"id":"68b340c8-3a31-4d54-abb9-b25a0fbbe60a","type":"trifecta","key":[3,1,9],"odds":44.3},{"id":"68b92443-5412-4292-b0b9-45611bd4d923","type":"trifecta","key":[8,6,3],"odds":180.2},{"id":"68e9c7ce-3f66-4f1a-87f8-798119381999","type":"trifecta","key":[1,8,5],"odds":131.3},{"id":"6905d85a-c36a-4f72-8012-8cac1a82cbc9","type":"trifecta","key":[2,4,6],"odds":146.5},{"id":"6aade384-61e9-4f55-93fb-fc572bd04152","type":"trifecta","key":[3,4,8],"odds":190.8},{"id":"6b134dc4-4d9f-4ef5-8d09-7f21a3517cfb","type":"trifecta","key":[9,5,8],"odds":129.5},{"id":"6b1d8950-8794-440d-b7e8-61506f687961","type":"trifecta","key":[6,5,3],"odds":103.4},{"id":"6b7e4882-27c9-4669-aac5-ff7c2b896bb9","type":"trifecta","key":[6,4,9],"odds":125.3},{"id":"6bb53a24-f9f3-4e7d-8ce1-d67278ce43bf","type":"trifecta","key":[5,6,3],"odds":290.1},{"id":"6c16170c-7336-4fb1-a60b-2bc93dff4ec8","type":"trifecta","key":[9,6,8],"odds":295.8},{"id":"6ce115b7-2bdc-4839-adfd-926ead3ac550","type":"trifecta","key":[8,9,5],"odds":69},{"id":"6dc8d33e-f5cd-4198-ab0a-35c763d9b3e8","type":"trifecta","key":[4,6,8],"odds":117.4},{"id":"6dcd8a07-bbdb-45f0-8079-771d9934e0c6","type":"trifecta","key":[4,5,8],"odds":204.2},{"id":"6e47c3b3-27c4-448a-9cd8-23764ca96d15","type":"trifecta","key":[1,5,6],"odds":166.9},{"id":"6f42e1b7-3d7d-4b37-9b0e-30d3fc6f45a2","type":"trifecta","key":[5,6,4],"odds":151.1},{"id":"6f88ba51-4824-4658-a0be-816947115992","type":"trifecta","key":[5,1,7],"odds":285.7},{"id":"703eb6c7-d1f0-4aeb-bebf-bdb23c6522be","type":"trifecta","key":[9,4,6],"odds":196.5},{"id":"70c0b366-af39-46eb-980d-ae4b0206e0c8","type":"trifecta","key":[4,7,9],"odds":77.7},{"id":"72d23034-8a40-4a12-bcdb-9940ffeb6028","type":"trifecta","key":[4,6,5],"odds":79.1},{"id":"7302f40e-79c1-40fb-b37f-6b4a405d0fc9","type":"trifecta","key":[1,8,9],"odds":163.8},{"id":"7367c9d7-7ae0-4f98-965f-e9d4be253715","type":"trifecta","key":[2,1,3],"odds":260.3},{"id":"73d10e01-ab50-47bc-911a-2c8c944e5b30","type":"trifecta","key":[3,7,2],"odds":223.2},{"id":"741721bc-d7aa-45e5-b7bc-ac981c73b251","type":"trifecta","key":[2,4,3],"odds":196.3},{"id":"747f9e12-e165-4478-b258-51ac60c5dd6e","type":"trifecta","key":[4,6,3],"odds":66.2},{"id":"7497a3ff-bea6-4804-9786-e3627d053bca","type":"trifecta","key":[8,5,9],"odds":75},{"id":"75d2e142-6215-459c-b222-3c2280436f56","type":"trifecta","key":[1,3,7],"odds":259.2},{"id":"766dc187-df2b-41ee-a0f0-1930d438ec4b","type":"trifecta","key":[7,6,4],"odds":130.7},{"id":"766e345e-a1fa-4d4b-906c-fd9a3ad15e38","type":"trifecta","key":[9,8,1],"odds":179.5},{"id":"76e33f91-be90-4e14-bb99-18df25892db5","type":"trifecta","key":[6,7,2],"odds":94.6},{"id":"76ffb49d-e8f6-4c67-b896-bef4fcea3dda","type":"trifecta","key":[6,8,4],"odds":175.3},{"id":"7773b3b0-c35b-44f1-9b29-681e1d6188fc","type":"trifecta","key":[1,2,5],"odds":125.9},{"id":"779fda87-fcce-4912-8146-24ba8970a24c","type":"trifecta","key":[7,9,8],"odds":44.7},{"id":"77f1b1e2-46c3-42eb-b236-1d0d9f302548","type":"trifecta","key":[6,2,4],"odds":78.9},{"id":"780172fc-b4a0-4958-bbd6-f5374f8ecb22","type":"trifecta","key":[2,3,7],"odds":115},{"id":"783d8bc3-80e1-4698-8abc-e0255a629153","type":"trifecta","key":[1,7,8],"odds":50.8},{"id":"7a7219b9-3cd7-47d9-9b28-fd4907180f20","type":"trifecta","key":[2,3,8],"odds":149.2},{"id":"7ad8b419-3f4f-4df9-9182-8803aa0536b5","type":"trifecta","key":[1,3,5],"odds":145},{"id":"7b1f1332-d464-459a-b678-fa1e5f268f18","type":"trifecta","key":[8,3,7],"odds":51.5},{"id":"7c1a2fc6-4e61-435c-b688-2b2d9acb9f59","type":"trifecta","key":[2,9,1],"odds":251.8},{"id":"7cb9d1d4-1a43-4b96-8d43-a251423e0124","type":"trifecta","key":[4,6,7],"odds":129.4},{"id":"7cfaa372-cf5f-4ab7-a1ba-2479c010ea2c","type":"trifecta","key":[4,8,5],"odds":124.2},{"id":"7d0eae56-e85d-4961-b84b-d71cae96e319","type":"trifecta","key":[8,2,6],"odds":57},{"id":"7daadbe8-c7db-4972-8f6c-e9b3b773f95b","type":"trifecta","key":[8,2,7],"odds":268.5},{"id":"7dc5300b-edae-4a7a-ba03-bcbf86341f4f","type":"trifecta","key":[6,5,4],"odds":181.8},{"id":"7e06d5e2-b2d7-419e-aa4d-6c275eb3f7e5","type":"trifecta","key":[2,9,8],"odds":88.6},{"id":"7e358c87-42c6-433e-b23e-d4586b77a05e","type":"trifecta","key":[5,2,7],"odds":29},{"id":"7eada7a6-c212-4b19-b0a6-242982828bf9","type":"trifecta","key":[6,4,7],"odds":171.6},{"id":"7f2528e8-a2e4-4534-b6c7-ba78a1250112","type":"trifecta","key":[5,1,8],"odds":101.9},{"id":"7f3ce18d-273a-4281-96ba-a15d1f9af2dd","type":"trifecta","key":[5,7,1],"odds":197},{"id":"7fba0752-69d5-4611-aaa9-c4c756930e8e","type":"trifecta","key":[6,1,3],"odds":134.4},{"id":"8055a115-3b33-414e-b874-9243a4be0140","type":"trifecta","key":[6,8,7],"odds":26},{"id":"8175082c-566c-4f86-a405-18926101c42a","type":"trifecta","key":[9,3,5],"odds":163.3},{"id":"81f8fc15-f831-48ec-8425-bfef79992058","type":"trifecta","key":[8,2,1],"odds":244.2},{"id":"82e30b49-022e-4e1a-8e11-4345651d9ee3","type":"trifecta","key":[5,4,9],"odds":133.5},{"id":"832986f1-2123-4508-af0d-e7d32d4becb8","type":"trifecta","key":[7,1,3],"odds":219.7},{"id":"834fc009-86c6-4e11-b6c5-8858f7baa9fa","type":"trifecta","key":[3,9,7],"odds":54},{"id":"8457015c-03cc-4ae1-8edd-53cae35f75cf","type":"trifecta","key":[1,2,4],"odds":141.3},{"id":"8582ec77-c458-48c1-a658-c74d5f994176","type":"trifecta","key":[5,9,6],"odds":218.5},{"id":"8635fb85-8093-4e66-bd96-304b4e35d8e3","type":"trifecta","key":[9,4,2],"odds":150.8},{"id":"87a65349-2348-454f-8097-9c040d81d1c5","type":"trifecta","key":[9,5,7],"odds":56.8},{"id":"87e31ab6-b5bb-458c-8c2f-78d1902b08f2","type":"trifecta","key":[4,6,2],"odds":133.3},{"id":"88099358-6eac-4bb9-804c-2484c4cb50c5","type":"trifecta","key":[3,7,1],"odds":136.1},{"id":"88514b70-d3df-42cf-b03f-3443e5317422","type":"trifecta","key":[6,5,2],"odds":241.8},{"id":"897fbaec-5bd0-4b97-86a3-b177b157013a","type":"trifecta","key":[7,4,9],"odds":6.9},{"id":"89bef5b4-95cb-4b20-88dd-18ff355d90dd","type":"trifecta","key":[5,3,4],"odds":259.5},{"id":"8a054713-ba49-49c0-81fd-7bba0ca1204d","type":"trifecta","key":[9,6,2],"odds":5.3},{"id":"8a14530b-310e-421a-9f61-369e3653fdc9","type":"trifecta","key":[8,5,7],"odds":91},{"id":"8c684956-dbc8-48d6-88f7-2b2d2cbc4579","type":"trifecta","key":[3,7,6],"odds":7.3},{"id":"8d396b13-2fb2-40be-b7d8-57315fa179e3","type":"trifecta","key":[7,5,2],"odds":178.9},{"id":"8e3b44d4-1187-4695-aa99-cf30726b3613","type":"trifecta","key":[1,6,7],"odds":12.8},{"id":"8f5d35d3-da37-43c0-9448-6dce5a3cf3a2","type":"trifecta","key":[8,5,2],"odds":93.5},{"id":"8f910863-d556-4518-ab65-75ae93ea772b","type":"trifecta","key":[5,2,8],"odds":49.4},{"id":"8fdb99df-975c-4717-ab72-3baee969b7e9","type":"trifecta","key":[8,5,4],"odds":37.8},{"id":"9085b762-aaac-4ae2-a2dd-b4cb2d479975","type":"trifecta","key":[4,9,6],"odds":186.1},{"id":"90a957a2-661b-4409-b775-b294f70625f6","type":"trifecta","key":[6,9,4],"odds":184.4},{"id":"90ada1d5-f0e1-4bb7-9553-08bdb83b6f16","type":"trifecta","key":[2,8,5],"odds":178.9},{"id":"90cb1fbe-ff86-4c36-a9c1-ca79038ccc7d","type":"trifecta","key":[5,8,6],"odds":216.7},{"id":"913c1d87-8bae-40ea-be6d-67504917bcfe","type":"trifecta","key":[2,8,9],"odds":15},{"id":"9236dcea-9aad-4a81-9ae6-07e19fe3bacc","type":"trifecta","key":[8,5,3],"odds":288.8},{"id":"92384b09-cca2-4d0b-86cd-342593abcfab","type":"trifecta","key":[5,4,1],"odds":186},{"id":"93bb9696-cb6c-4611-817e-86ddcca2fa37","type":"trifecta","key":[7,2,9],"odds":288.8},{"id":"941cbb8c-b60c-4f73-81b0-53dbae8b5d68","type":"trifecta","key":[8,6,5],"odds":150},{"id":"946877d8-8780-42a3-90ca-c2a2358e0448","type":"trifecta","key":[7,3,2],"odds":84.8},{"id":"948f8179-7c63-4139-ae47-5dd7c12627d6","type":"trifecta","key":[5,4,2],"odds":102},{"id":"94e09aa9-53b3-4abe-b2f4-a97a94573d3f","type":"trifecta","key":[5,7,4],"odds":268.2},{"id":"96fd4aa6-8b48-4d42-b68e-02dfb720887b","type":"trifecta","key":[1,9,5],"odds":87.5},{"id":"9793fb83-cd25-4679-af14-0d5996050be2","type":"trifecta","key":[8,3,1],"odds":50.1},{"id":"97b61f91-e5a5-4f5a-8900-d7e357f8e793","type":"trifecta","key":[7,4,5],"odds":149.1},{"id":"97f6bfeb-f5fe-4d68-8cab-7c70a5baa91a","type":"trifecta","key":[4,8,1],"odds":13},{"id":"9809b8da-726f-4683-9d7d-3d0e4f8fb216","type":"trifecta","key":[6,3,8],"odds":32},{"id":"98c17c22-2454-4217-9553-441bba4763f0","type":"trifecta","key":[1,6,3],"odds":204},{"id":"9950c552-45b2-4ea8-9e25-fd9b4677e237","type":"trifecta","key":[1,4,3],"odds":144.4},{"id":"9983a7a6-a3fd-4ad8-9a03-2fd0b06f88e4","type":"trifecta","key":[1,7,9],"odds":111.4},{"id":"9cc85757-2b4f-46c1-b0c5-e81b42130d39","type":"trifecta","key":[6,4,8],"odds":42.7},{"id":"9dec2c0f-47ab-4006-b82c-3374861a87b6","type":"trifecta","key":[5,3,6],"odds":63.7},{"id":"9e57fada-8556-486d-976c-5764080de37d","type":"trifecta","key":[8,5,1],"odds":209.7},{"id":"9eb03505-5620-4270-b1a4-8d30882aa7d6","type":"trifecta","key":[5,9,8],"odds":269.2},{"id":"9ec9cac3-1a1a-4d3e-8995-12cbaa0c8d60","type":"trifecta","key":[3,8,4],"odds":298.8},{"id":"9f8ee4e2-98e3-4075-89fa-a312a891b0e0","type":"trifecta","key":[4,2,7],"odds":29.2},{"id":"a0807f48-0467-476f-8eda-5122ea51564e","type":"trifecta","key":[8,7,1],"odds":98.1},{"id":"a1521998-f44e-4771-958c-0c336226200a","type":"trifecta","key":[9,2,6],"odds":82.8},{"id":"a174d02c-4197-4f59-9096-63c04f25019a","type":"trifecta","key":[2,3,1],"odds":79.3},{"id":"a30c483a-a8c8-476d-849e-b7f65b4403f5","type":"trifecta","key":[4,9,1],"odds":72.6},{"id":"a340ce4c-3f29-4657-8a4e-7aa9a9f6960d","type":"trifecta","key":[1,4,8],"odds":169.6},{"id":"a3565ff3-a41c-457b-87c0-b09b23df4bd1","type":"trifecta","key":[4,7,1],"odds":235.7},{"id":"a39db4d0-59f7-42ad-847a-0cd2d8906911","type":"trifecta","key":[4,7,5],"odds":31.6},{"id":"a3ba882b-02a3-42b4-b793-fc1a7f711e65","type":"trifecta","key":[2,3,9],"odds":7.3},{"id":"a3c348cc-4ec4-4341-9f82-f37cc0d8a0a5","type":"trifecta","key":[9,8,5],"odds":262.3},{"id":"a4dd8d37-60f6-4a0c-aebc-35afcd88fe0e","type":"trifecta","key":[6,7,4],"odds":227.2},{"id":"a5374930-514d-4c47-88c9-54098f2b0998","type":"trifecta","key":[1,3,4],"odds":12.3},{"id":"a5d36ef8-c842-463f-835b-2188bcabb866","type":"trifecta","key":[2,6,4],"odds":273.3},{"id":"a67e84bc-f4c4-4ae2-a2de-cfa20232c922","type":"trifecta","key":[3,4,5],"odds":149},{"id":"a715cef7-61a9-4157-9e7d-1a34bfb43879","type":"trifecta","key":[7,3,5],"odds":106.5},{"id":"a758a04c-c46d-49b8-bfa3-fbe1d0436758","type":"trifecta","key":[6,1,4],"odds":277.8},{"id":"a869d21c-7b53-4926-b43b-522d71a758e3","type":"trifecta","key":[3,1,7],"odds":299.5},{"id":"a9be94ea-523a-4a2c-a92b-a32c9911b3dd","type":"trifecta","key":[4,3,6],"odds":99.8},{"id":"a9ebb489-99c6-4fca-a440-5a6f9f69e193","type":"trifecta","key":[6,2,5],"odds":255.3},{"id":"aa2fad56-a87d-4949-9bea-987721642b52","type":"trifecta","key":[5,2,4],"odds":173.6},{"id":"aafdfdd7-aa9b-4959-9417-4f12175f1b84","type":"trifecta","key":[7,9,2],"odds":65},{"id":"ab23c866-15b7-4355-bd54-1e12fa125d8c","type":"trifecta","key":[9,1,5],"odds":100},{"id":"abf6f1e2-5839-4513-a678-9a30bbee7f27","type":"trifecta","key":[5,4,7],"odds":203},{"id":"ac2a0f77-9565-474a-b70f-1e37dc8de769","type":"trifecta","key":[4,9,5],"odds":204.9},{"id":"ad53fc7b-a071-46fa-b375-077f7c7ee3b7","type":"trifecta","key":[8,4,7],"odds":99.9},{"id":"ada60cff-64ff-4f4b-bcf6-14356d11ac05","type":"trifecta","key":[5,2,1],"odds":166.6},{"id":"aeb8ca02-71b9-4b54-9bf0-a02fec4cdbdc","type":"trifecta","key":[4,8,3],"odds":205},{"id":"aec9a8ad-902e-4885-8fac-7bd43e6e6eb6","type":"trifecta","key":[2,5,3],"odds":35.1},{"id":"aed0cc00-fc88-4ded-907e-25a83e916346","type":"trifecta","key":[1,6,2],"odds":238.8},{"id":"aedc2ba0-bad4-4965-a1b4-3ef607170b93","type":"trifecta","key":[7,5,4],"odds":139.1},{"id":"af17dc28-c691-4fe0-8ce8-199954d2ba81","type":"trifecta","key":[4,8,2],"odds":31.9},{"id":"af29ca20-de4f-4255-9723-bd930f57f0e0","type":"trifecta","key":[3,8,5],"odds":22.5},{"id":"b0b467b3-9bc6-4ca1-9e86-d6a3b8861e76","type":"trifecta","key":[8,6,4],"odds":113.5},{"id":"b24cab19-2a35-4624-92dd-346beda1fa9f","type":"trifecta","key":[6,8,5],"odds":263.7},{"id":"b2b6ad57-85b4-4a7f-bdfd-cae33d946da0","type":"trifecta","key":[9,7,5],"odds":243.2},{"id":"b3c5f8ab-b096-4812-895d-65142fe72936","type":"trifecta","key":[6,7,8],"odds":12.3},{"id":"b42db033-c34e-4eaa-b072-37f7926b6385","type":"trifecta","key":[6,5,7],"odds":64.3},{"id":"b47c2dff-d770-4a62-82f4-8949ab46c4e3","type":"trifecta","key":[5,2,3],"odds":198.8},{"id":"b4e5ac16-b78c-43ce-9be2-b492d203cccc","type":"trifecta","key":[6,8,1],"odds":9.2},{"id":"b5c171ac-05d0-43fb-af9d-611de49793bb","type":"trifecta","key":[3,1,6],"odds":64.1},{"id":"b6b03294-315f-4d87-94df-f2b956088ce5","type":"trifecta","key":[8,9,6],"odds":74},{"id":"b6e18bff-7010-4c8d-9dd8-6199adf8a344","type":"trifecta","key":[2,5,1],"odds":46.8},{"id":"b77a2c74-b525-465b-83e4-ad75527d6c7a","type":"trifecta","key":[5,3,2],"odds":233.2},{"id":"b7e65353-dc9c-458a-ba88-75390b7c26ac","type":"trifecta","key":[1,9,6],"odds":125.9},{"id":"b7f9582a-9d4c-4d38-8042-b5baee45513c","type":"trifecta","key":[7,3,4],"odds":26.9},{"id":"b87f2ebd-7628-462f-880d-920dcadcb02b","type":"trifecta","key":[4,5,6],"odds":56},{"id":"ba149758-94b5-4a29-8dd6-7bbbb800c87c","type":"trifecta","key":[2,6,9],"odds":29.5},{"id":"bab432f8-4dd6-4a42-b1cd-230a75eed97d","type":"trifecta","key":[3,2,1],"odds":77.6},{"id":"baf549bd-f0e2-4507-b788-ae9ec4f46b66","type":"trifecta","key":[3,5,8],"odds":245.2},{"id":"bb15200d-3267-45b8-9fef-8ed74873e81c","type":"trifecta","key":[2,4,7],"odds":136.3},{"id":"bb414280-c073-4d03-8ffa-71d1c5e98a23","type":"trifecta","key":[6,1,2],"odds":268.6},{"id":"bb64daed-615b-45a4-a477-73b9e1eedd27","type":"trifecta","key":[1,6,8],"odds":192.1},{"id":"bb708407-d189-4a58-8cf7-a19f4f12841d","type":"trifecta","key":[4,2,9],"odds":56.7},{"id":"bb9c2612-1d2d-40d5-b26a-d78eb30ec37a","type":"trifecta","key":[4,3,9],"odds":89.5},{"id":"bc5fe3e9-081a-4a13-8d0f-54f4466a1aa6","type":"trifecta","key":[1,5,3],"odds":178.9},{"id":"bf8907d4-ec85-438f-831b-d1fdc7d02e7b","type":"trifecta","key":[1,2,9],"odds":279.1},{"id":"c157963e-95aa-4e68-87bf-12413753b5ca","type":"trifecta","key":[4,3,1],"odds":197.1},{"id":"c1f1ace6-5d5d-4652-9e12-59fe11b9a1d4","type":"trifecta","key":[7,9,3],"odds":99},{"id":"c28d17d1-bd7a-4feb-aa14-4ab974434306","type":"trifecta","key":[3,7,5],"odds":297},{"id":"c2a6cd93-5c99-42f2-9672-db6e7e887d7a","type":"trifecta","key":[7,5,3],"odds":57.9},{"id":"c2db5ce7-fa13-4459-a49b-3d731f10318a","type":"trifecta","key":[1,2,7],"odds":16.4},{"id":"c340a697-9703-4925-bcde-658eda99836c","type":"trifecta","key":[1,2,3],"odds":128},{"id":"c456dcab-9c3f-4578-aa78-74db7d516045","type":"trifecta","key":[5,3,8],"odds":38.8},{"id":"c4871f20-d3da-49ea-ab5d-b2481172f33c","type":"trifecta","key":[4,6,1],"odds":63},{"id":"c489d1ad-577f-4360-8865-9ad109a21777","type":"trifecta","key":[7,8,5],"odds":293.5},{"id":"c5013e14-cdaf-4596-a616-9898c981353d","type":"trifecta","key":[7,6,8],"odds":4.4},{"id":"c522317b-3bf6-4d55-8b29-70a4f7bd1ecd","type":"trifecta","key":[8,1,2],"odds":294.2},{"id":"c57eb8fc-fe78-48af-a4af-8e3a7d462985","type":"trifecta","key":[4,1,7],"odds":104.7},{"id":"c5af687e-1962-4491-9d17-743b61ac1428","type":"trifecta","key":[8,4,3],"odds":255},{"id":"c5e40fb1-1409-407a-88b3-8c204f8f8cbe","type":"trifecta","key":[6,3,2],"odds":16.2},{"id":"c5ea7be5-868e-4129-a430-143ff5bfb566","type":"trifecta","key":[1,4,6],"odds":178.7},{"id":"c78ce11f-62f7-4913-80e2-dd57f90c9f9a","type":"trifecta","key":[5,9,2],"odds":240.2},{"id":"c7e23156-a7f1-4347-b35b-187dbfdf2320","type":"trifecta","key":[8,7,5],"odds":146.6},{"id":"c82d0461-29fa-48c0-8e93-72db04ed8908","type":"trifecta","key":[1,9,3],"odds":82.6},{"id":"c8593ddb-f64a-4071-920f-8191ea1b2c0e","type":"trifecta","key":[3,9,2],"odds":90.5},{"id":"c942fda3-4e56-4f97-990a-2e17178dc63f","type":"trifecta","key":[4,1,3],"odds":155.7},{"id":"c9a07335-723d-4828-ac57-03b9cc695223","type":"trifecta","key":[9,2,5],"odds":39},{"id":"c9d3e79b-542c-4661-b18a-27bcdf771c61","type":"trifecta","key":[6,5,8],"odds":185.4},{"id":"c9f24222-d00b-4ae2-a5bb-d50fe04a42c2","type":"trifecta","key":[8,3,9],"odds":63.4},{"id":"ca22418b-fa37-4b9c-8790-0b5f589d0ad9","type":"trifecta","key":[5,8,1],"odds":132.5},{"id":"caa0974a-db37-404f-bec2-4f89069ab007","type":"trifecta","key":[4,2,6],"odds":61.8},{"id":"cc4eddc6-8a0d-4f85-88b1-4f9f67f6aaf9","type":"trifecta","key":[6,3,9],"odds":95.8},{"id":"cc4ef1b1-61b6-44fd-8521-952bda438e9f","type":"trifecta","key":[1,9,7],"odds":95},{"id":"cd28a41b-87bc-434d-b660-42561e40bf2f","type":"trifecta","key":[7,5,1],"odds":115.7},{"id":"cd825f45-cf6b-4e24-962e-613ab08e7c89","type":"trifecta","key":[9,7,2],"odds":27.8},{"id":"cde5b911-bc4a-49c5-b7d7-db4932041bc3","type":"trifecta","key":[7,9,6],"odds":202.3},{"id":"cdedfb22-fa23-475d-8ba1-95d6504be7e1","type":"trifecta","key":[8,7,3],"odds":133.3},{"id":"ce5d199f-9fb0-4b57-93db-44064bf015d2","type":"trifecta","key":[8,1,4],"odds":44.9},{"id":"cece4726-fbae-476b-aa32-7a47fdb452ec","type":"trifecta","key":[7,8,2],"odds":267.8},{"id":"cf9146a5-f7af-41a2-9111-cc232eaa257d","type":"trifecta","key":[5,9,4],"odds":31.2},{"id":"cff59e29-6ed1-42ef-a6e9-1d992ac7c386","type":"trifecta","key":[3,8,6],"odds":9.3},{"id":"d053195e-076c-48f8-980a-f0ca7f0135c8","type":"trifecta","key":[8,1,7],"odds":27.2},{"id":"d05b274e-0ac4-4dd6-a458-565766fe6c99","type":"trifecta","key":[9,5,3],"odds":76.9},{"id":"d0756efc-84e0-48f7-bebd-09a3e536213d","type":"trifecta","key":[5,8,9],"odds":56.8},{"id":"d0fce5e1-bfff-477d-9fbc-6524f5ae8fc7","type":"trifecta","key":[7,3,1],"odds":24.5},{"id":"d17d5c9c-2ed2-4d9b-b623-609887af65d3","type":"trifecta","key":[2,6,8],"odds":172.6},{"id":"d27cf4e0-ac4f-415f-8316-31028c55ff9f","type":"trifecta","key":[9,1,3],"odds":224.4},{"id":"d2b07257-0a09-4ed5-b59c-976da61cb29c","type":"trifecta","key":[3,5,2],"odds":167.8},{"id":"d32bec2a-6565-4c81-a8b0-37f89693a833","type":"trifecta","key":[2,1,8],"odds":282.6},{"id":"d367fead-1696-4b30-93bf-43653f4487ac","type":"trifecta","key":[1,7,4],"odds":179},{"id":"d3c85689-0702-407f-949e-0b7a1f15e10b","type":"trifecta","key":[6,1,7],"odds":263.9},{"id":"d49d0476-0e5c-4bba-b6f7-ac90ffde7f86","type":"trifecta","key":[3,2,7],"odds":58.6},{"id":"d4be084a-1502-4e1b-a829-240a987150d6","type":"trifecta","key":[1,9,2],"odds":229.5},{"id":"d4f5e68e-c46a-460a-ad47-f62037a714b1","type":"trifecta","key":[1,7,6],"odds":236.3},{"id":"d50771be-2a0f-4462-bc79-6d152469e505","type":"trifecta","key":[7,8,6],"odds":189.2},{"id":"d5fad363-7a93-44c5-8b04-2bb01f050ebc","type":"trifecta","key":[2,8,7],"odds":271.8},{"id":"d77a7e0d-4e40-425d-bd7a-3e1f90434a23","type":"trifecta","key":[3,6,5],"odds":57.2},{"id":"d7d246f7-b075-4dab-a024-720a9f604e1b","type":"trifecta","key":[5,3,7],"odds":91.3},{"id":"d8c3071a-7918-4414-9bab-d0163ddad10a","type":"trifecta","key":[6,5,9],"odds":210.5},{"id":"da41e0bd-4e99-480c-b50e-43e656db8f07","type":"trifecta","key":[5,1,3],"odds":15.5},{"id":"da70156b-671c-4ee0-8d95-0221727fd783","type":"trifecta","key":[2,1,6],"odds":190.6},{"id":"da904ac6-6acf-4780-9fd0-0639358f3335","type":"trifecta","key":[1,7,3],"odds":299.4},{"id":"db43dcc1-7c35-49ff-9fb8-d25ec303e9ca","type":"trifecta","key":[2,9,4],"odds":212.6},{"id":"dbb8d689-1178-434b-9681-ea3d96a37c7e","type":"trifecta","key":[6,3,5],"odds":124.4},{"id":"dc4af142-6ead-4349-bbb2-a524214b01b3","type":"trifecta","key":[9,2,8],"odds":213.8},{"id":"dc5792c4-93fd-42b6-a060-661802820b23","type":"trifecta","key":[8,2,9],"odds":269.6},{"id":"dcd0fe5a-7aef-449f-b35c-0c5a39e0ade6","type":"trifecta","key":[9,5,1],"odds":248.8},{"id":"dd011c41-2752-41a0-9afe-ad5d8bec5fc0","type":"trifecta","key":[9,6,4],"odds":165},{"id":"dd08a022-507a-4747-b0c8-2968e2849ad4","type":"trifecta","key":[7,6,5],"odds":150.1},{"id":"ddb0f54b-7226-49c7-90b8-f37b33be641d","type":"trifecta","key":[3,4,2],"odds":216.9},{"id":"ddc07fed-9f38-4490-be44-400daa053ec6","type":"trifecta","key":[3,5,6],"odds":207.5},{"id":"de0b892c-0a00-4a60-8055-619989b8c99c","type":"trifecta","key":[2,7,5],"odds":202.3},{"id":"de74d731-b250-43ef-9699-ddc0319d910b","type":"trifecta","key":[3,2,5],"odds":15.3},{"id":"de7dfc66-df83-499b-8082-8429cc1cf7a8","type":"trifecta","key":[9,7,1],"odds":85.2},{"id":"defd7361-00df-4278-9185-ff93c2f41f0b","type":"trifecta","key":[5,7,8],"odds":113.4},{"id":"e0c7bfc0-7898-4b35-8981-2d780482e2fc","type":"trifecta","key":[9,7,4],"odds":143},{"id":"e0efcaf2-df7e-416e-80cc-717ebea8c5c3","type":"trifecta","key":[1,8,4],"odds":177.7},{"id":"e12e6c5f-f9be-4e26-8012-61deaa6fd68a","type":"trifecta","key":[4,5,9],"odds":264.4},{"id":"e14f7272-25ef-493c-9173-cdf4021a52b2","type":"trifecta","key":[8,3,4],"odds":292},{"id":"e168be13-5e1a-4278-984b-f8b60406d02e","type":"trifecta","key":[9,8,6],"odds":23.6},{"id":"e2cd34f2-d1c6-467b-80ea-7a3e8a755da1","type":"trifecta","key":[2,1,4],"odds":277.7},{"id":"e3932671-90cd-42f0-bb67-c1e80da4afd5","type":"trifecta","key":[5,1,4],"odds":115.6},{"id":"e3a12189-5021-4cfb-a791-5d9aeb6bbce6","type":"trifecta","key":[7,2,8],"odds":220.1},{"id":"e5c60233-ec25-4426-ba0a-50ffb6963a87","type":"trifecta","key":[2,1,7],"odds":252.1},{"id":"e5c75411-79c7-441a-9416-d438550c2993","type":"trifecta","key":[9,8,4],"odds":123.3},{"id":"e6633584-349b-4127-b940-e352b67b0da1","type":"trifecta","key":[3,6,1],"odds":263.8},{"id":"e683ef64-6d4c-4662-bb22-7360c0cb01da","type":"trifecta","key":[8,4,1],"odds":159.1},{"id":"e69aa743-9ad3-42bd-beca-247c5399fac7","type":"trifecta","key":[4,1,8],"odds":261.8},{"id":"e6cf0cf4-7068-4103-bcc4-da7816beed91","type":"trifecta","key":[4,1,5],"odds":239.1},{"id":"e6e660c1-0b46-4364-8980-5222156822df","type":"trifecta","key":[3,1,4],"odds":210.2},{"id":"e78e0bf5-7b5a-4cfa-bd31-64d8859fe9c5","type":"trifecta","key":[3,9,1],"odds":8.1},{"id":"e79b75c3-ce01-43d5-8bf6-cbf7100ca9fc","type":"trifecta","key":[7,2,4],"odds":81.9},{"id":"e8e8b311-366a-47b5-b8e2-fb85c061ada2","type":"trifecta","key":[8,3,2],"odds":192},{"id":"e90df722-be90-49a3-bccb-08cd59e72891","type":"trifecta","key":[8,5,6],"odds":112.9},{"id":"e92e0997-765a-49f5-a43a-473831e0b9e6","type":"trifecta","key":[8,7,4],"odds":195.9},{"id":"e97a2778-c5e0-4f9c-bbeb-3b6cf36527cd","type":"trifecta","key":[3,9,8],"odds":292.6},{"id":"e9e9e473-3f4d-4f21-bcca-8d406bd41bac","type":"trifecta","key":[9,1,6],"odds":188.6},{"id":"ea4c55f7-25e7-4daa-8bc8-e33718b441b7","type":"trifecta","key":[8,6,2],"odds":175.8},{"id":"ea7c56ec-f53c-43e3-a96c-3fd23e484b8b","type":"trifecta","key":[8,3,5],"odds":284.3},{"id":"ea7cbef5-0c12-4005-87c6-fbb7f2108978","type":"trifecta","key":[3,7,8],"odds":9.2},{"id":"eb81eac0-c563-45fc-b685-6dff9714c0d4","type":"trifecta","key":[9,8,7],"odds":249.5},{"id":"ebc8333a-4ce9-4fea-a566-6fb5a7f4b8fd","type":"trifecta","key":[8,1,6],"odds":227.3},{"id":"ebeb9cad-b9ff-4a49-9c45-3838cdd6f7e6","type":"trifecta","key":[4,5,2],"odds":43.5},{"id":"ebed1431-210b-4b52-bff3-1a1a1b760be3","type":"trifecta","key":[6,7,3],"odds":47.4},{"id":"ec05b68e-8433-489e-8cc1-e9adf5a44358","type":"trifecta","key":[9,5,6],"odds":73.9},{"id":"ec2719b5-f457-4ed7-be94-f55dfe2bfa01","type":"trifecta","key":[6,4,5],"odds":245.8},{"id":"eca451ee-6dd2-4814-aec7-c71531b1b4e7","type":"trifecta","key":[1,6,4],"odds":180.1},{"id":"ede0025c-c013-4a73-ae9b-5f8f7999512b","type":"trifecta","key":[9,2,1],"odds":78.7},{"id":"ee309ffb-a8b3-4137-b2a0-bbb86e746708","type":"trifecta","key":[5,6,9],"odds":87.7},{"id":"ef7c572f-ac3f-440c-86d5-02b75fe683a9","type":"trifecta","key":[8,1,3],"odds":64.3},{"id":"f1a07695-eeb5-412c-86a3-34df9e043b15","type":"trifecta","key":[2,8,4],"odds":275.5},{"id":"f1ba7e60-6078-48c8-9200-7b7a9fd4d97c","type":"trifecta","key":[8,7,6],"odds":77.9},{"id":"f24ce97c-f918-4394-a782-2b0cf043a648","type":"trifecta","key":[3,9,6],"odds":1.4},{"id":"f28f5609-f90e-4fa1-8e72-a27b8941ca8a","type":"trifecta","key":[4,5,1],"odds":233.4},{"id":"f2da55e8-8e74-4aff-8fcc-6f40575f05e8","type":"trifecta","key":[1,8,6],"odds":279.6},{"id":"f32830ff-a45a-4e4c-ab56-6ae1116f99e6","type":"trifecta","key":[3,2,4],"odds":165.5},{"id":"f354bb8b-7f62-40e3-9453-043e2e7d70a3","type":"trifecta","key":[3,8,2],"odds":30},{"id":"f35a6b74-7713-463d-851b-23148893760d","type":"trifecta","key":[6,3,7],"odds":218.3},{"id":"f3f5bcbf-d480-4360-b610-54d76e02359e","type":"trifecta","key":[2,9,7],"odds":47},{"id":"f43920a8-70c9-4c46-860a-3e51867061c1","type":"trifecta","key":[9,3,1],"odds":61.5},{"id":"f489cb3f-5e42-472d-ab21-4a0fd6c70afd","type":"trifecta","key":[1,4,9],"odds":195.6},{"id":"f4b12030-fd7b-4b30-894d-4f9e03c61b0d","type":"trifecta","key":[3,7,4],"odds":139.5},{"id":"f50b4ad9-84e9-4d90-83fa-0b1c07806403","type":"trifecta","key":[4,5,7],"odds":126.9},{"id":"f52a08b5-3305-4552-a337-6b43bcfaed55","type":"trifecta","key":[2,3,4],"odds":17.1},{"id":"f5f6ccd4-bd4c-496a-aca5-40ccedf43d30","type":"trifecta","key":[6,3,4],"odds":125.2},{"id":"f624ce3e-5d7b-421e-a628-dcc67158915b","type":"trifecta","key":[3,5,4],"odds":149.1},{"id":"f74004f6-0ced-412a-a097-bbd6755ffbc1","type":"trifecta","key":[9,1,7],"odds":117.4},{"id":"f78a2a37-1175-4ade-b7cc-18affedefaa7","type":"trifecta","key":[2,6,3],"odds":291.6},{"id":"f83eef19-1128-47f8-8f6c-f971f67d6c3c","type":"trifecta","key":[2,3,5],"odds":119.5},{"id":"f890ee39-3c8d-458a-aa52-e9bd7bd76e14","type":"trifecta","key":[2,4,9],"odds":120.7},{"id":"f8f5cf2a-14d5-45ff-8207-78fc08dfc6d9","type":"trifecta","key":[2,7,9],"odds":47.3},{"id":"f90a9bd9-49ba-4b3b-97fc-7029e5a96433","type":"trifecta","key":[7,1,8],"odds":46.8},{"id":"f9371c80-1f03-462e-909a-02f879c96ddc","type":"trifecta","key":[6,1,9],"odds":110.7},{"id":"f98bf20b-ca72-4c2f-b408-3cd2da344fcb","type":"trifecta","key":[4,7,3],"odds":88.7},{"id":"faa70ab7-8af4-4a70-9d26-d3de4ba2fa5a","type":"trifecta","key":[6,8,3],"odds":161.4},{"id":"fb346ca6-3bb9-4b77-880b-f92477530757","type":"trifecta","key":[3,4,7],"odds":38.6},{"id":"fb586c45-acfd-4876-9aa5-a4e373df35bd","type":"trifecta","key":[6,9,3],"odds":103.8},{"id":"fc042824-09b6-4458-80f6-56a8acb9a53f","type":"trifecta","key":[6,9,5],"odds":251.5},{"id":"fc59a4b6-b541-47af-898c-55eeec407309","type":"trifecta","key":[8,2,4],"odds":293.1},{"id":"fc7857ff-6532-431c-b34c-168d7b0fdf9d","type":"trifecta","key":[6,9,2],"odds":49.2},{"id":"fcf158fc-b206-417c-994e-9b51ae9a55f4","type":"trifecta","key":[4,8,9],"odds":280.1},{"id":"fd0d8866-cce1-4719-b3a9-d334a9c9b410","type":"trifecta","key":[5,1,2],"odds":81.6},{"id":"fd99f429-188b-4646-aeb3-0d92e5871b07","type":"trifecta","key":[1,6,9],"odds":254.3},{"id":"fdfc468f-4885-4821-8b3c-d6d4b8323f86","type":"trifecta","key":[2,9,6],"odds":166.2},{"id":"ff311b23-79ab-4a72-9463-c300622bfb0d","type":"trifecta","key":[3,6,7],"odds":176.3},{"id":"ff4a404e-9526-48bc-8386-cfe30a1e70dc","type":"trifecta","key":[6,1,8],"odds":101.1},{"id":"ff7f51eb-7a83-4334-ac7c-a1ae15ee2130","type":"trifecta","key":[7,4,8],"odds":150.8}]}